[{"name":{"common":"Aruba","official":"Aruba","native":{"nld":{"official":"Aruba","common":"Aruba"},"pap":{"official":"Aruba","common":"Aruba"}}},"cca2":"AW","independent":false,"status":"officially-assigned","currency":["AWG"],"capital":["Oranjestad"],"region":"Americas","subregion":"Caribbean","area":180},
{"name":{"common":"Afghanistan","official":"Islamic Republic of Afghanistan","native":{"prs":{"official":"\u062c\u0645\u0647\u0648\u0631\u06cc \u0627\u0633\u0644\u0627\u0645\u06cc \u0627\u0641\u063a\u0627\u0646\u0633\u062a\u0627\u0646","common":"\u0627\u0641\u063a\u0627\u0646\u0633\u062a\u0627\u0646"},"pus":{"official":"\u062f \u0627\u0641\u063a\u0627\u0646\u0633\u062a\u0627\u0646 \u0627\u0633\u0644\u0627\u0645\u064a \u062c\u0645\u0647\u0648\u0631\u06cc\u062a","common":"\u0627\u0641\u063a\u0627\u0646\u0633\u062a\u0627\u0646"},"tuk":{"official":"Owganystan Yslam Respublikasy","common":"Owganystan"}}},"cca2":"AF","independent":true,"status":"officially-assigned","currency":["AFN"],"capital":["Kabul"],"region":"Asia","subregion":"Southern Asia","area":652230},
{"name":{"common":"Angola","official":"Republic of Angola","native":{"por":{"official":"Rep\u00fablica de Angola","common":"Angola"}}},"cca2":"AO","independent":true,"status":"officially-assigned","currency":["AOA"],"capital":["Luanda"],"region":"Africa","subregion":"Middle Africa","area":1246700},
{"name":{"common":"Anguilla","official":"Anguilla","native":{"eng":{"official":"Anguilla","common":"Anguilla"}}},"cca2":"AI","independent":false,"status":"officially-assigned","currency":["XCD"],"capital":["The Valley"],"region":"Americas","subregion":"Caribbean","area":91},
{"name":{"common":"\u00c5land Islands","official":"\u00c5land Islands","native":{"swe":{"official":"Landskapet \u00c5land","common":"\u00c5land"}}},"cca2":"AX","independent":false,"status":"officially-assigned","currency":["EUR"],"capital":["Mariehamn"],"region":"Europe","subregion":"Northern Europe","area":1580},
{"name":{"common":"Albania","official":"Republic of Albania","native":{"sqi":{"official":"Republika e Shqip\u00ebris\u00eb","common":"Shqip\u00ebria"}}},"cca2":"AL","independent":true,"status":"officially-assigned","currency":["ALL"],"capital":["Tirana"],"region":"Europe","subregion":"Southern Europe","area":28748},
{"name":{"common":"Andorra","official":"Principality of Andorra","native":{"cat":{"official":"Principat d'Andorra","common":"Andorra"}}},"cca2":"AD","independent":true,"status":"officially-assigned","currency":["EUR"],"capital":["Andorra la Vella"],"region":"Europe","subregion":"Southern Europe","area":468},
{"name":{"common":"United Arab Emirates","official":"United Arab Emirates","native":{"ara":{"official":"\u0627\u0644\u0625\u0645\u0627\u0631\u0627\u062a \u0627\u0644\u0639\u0631\u0628\u064a\u0629 \u0627\u0644\u0645\u062a\u062d\u062f\u0629","common":"\u062f\u0648\u0644\u0629 \u0627\u0644\u0625\u0645\u0627\u0631\u0627\u062a \u0627\u0644\u0639\u0631\u0628\u064a\u0629 \u0627\u0644\u0645\u062a\u062d\u062f\u0629"}}},"cca2":"AE","independent":true,"status":"officially-assigned","currency":["AED"],"capital":["Abu Dhabi"],"region":"Asia","subregion":"Western Asia","area":83600},
{"name":{"common":"Argentina","official":"Argentine Republic","native":{"grn":{"official":"Argentine Republic","common":"Argentina"},"spa":{"official":"Rep\u00fablica Argentina","common":"Argentina"}}},"cca2":"AR","independent":true,"status":"officially-assigned","currency":["ARS"],"capital":["Buenos Aires"],"region":"Americas","subregion":"South America","area":2780400},
{"name":{"common":"Armenia","official":"Republic of Armenia","native":{"hye":{"official":"\u0540\u0561\u0575\u0561\u057d\u057f\u0561\u0576\u056b \u0540\u0561\u0576\u0580\u0561\u057a\u0565\u057f\u0578\u0582\u0569\u0575\u0578\u0582\u0576","common":"\u0540\u0561\u0575\u0561\u057d\u057f\u0561\u0576"}}},"cca2":"AM","independent":true,"status":"officially-assigned","currency":["AMD"],"capital":["Yerevan"],"region":"Asia","subregion":"Western Asia","area":29743},
{"name":{"common":"American Samoa","official":"American Samoa","native":{"eng":{"official":"American Samoa","common":"American Samoa"},"smo":{"official":"S\u0101moa Amelika","common":"S\u0101moa Amelika"}}},"cca2":"AS","independent":false,"status":"officially-assigned","currency":["USD"],"capital":["Pago Pago"],"region":"Oceania","subregion":"Polynesia","area":199},
{"name":{"common":"Antarctica","official":"Antarctica","native":[]},"cca2":"AQ","independent":false,"status":"officially-assigned","currency":[],"capital":[""],"region":"Antarctic","subregion":"","area":14000000},
{"name":{"common":"French Southern and Antarctic Lands","official":"Territory of the French Southern and Antarctic Lands","native":{"fra":{"official":"Territoire des Terres australes et antarctiques fran\u00e7aises","common":"Terres australes et antarctiques fran\u00e7aises"}}},"cca2":"TF","independent":false,"status":"officially-assigned","currency":["EUR"],"capital":["Port-aux-Fran\u00e7ais"],"region":"Antarctic","subregion":"","area":7747},
{"name":{"common":"Antigua and Barbuda","official":"Antigua and Barbuda","native":{"eng":{"official":"Antigua and Barbuda","common":"Antigua and Barbuda"}}},"cca2":"AG","independent":true,"status":"officially-assigned","currency":["XCD"],"capital":["Saint John's"],"region":"Americas","subregion":"Caribbean","area":442},
{"name":{"common":"Australia","official":"Commonwealth of Australia","native":{"eng":{"official":"Commonwealth of Australia","common":"Australia"}}},"cca2":"AU","independent":true,"status":"officially-assigned","currency":["AUD"],"capital":["Canberra"],"region":"Oceania","subregion":"Australia and New Zealand","area":7692024},
{"name":{"common":"Austria","official":"Republic of Austria","native":{"bar":{"official":"Republik \u00d6sterreich","common":"\u00d6sterreich"}}},"cca2":"AT","independent":true,"status":"officially-assigned","currency":["EUR"],"capital":["Vienna"],"region":"Europe","subregion":"Western Europe","area":83871},
{"name":{"common":"Azerbaijan","official":"Republic of Azerbaijan","native":{"aze":{"official":"Az\u0259rbaycan Respublikas\u0131","common":"Az\u0259rbaycan"},"rus":{"official":"\u0410\u0437\u0435\u0440\u0431\u0430\u0439\u0434\u0436\u0430\u043d\u0441\u043a\u0430\u044f \u0420\u0435\u0441\u043f\u0443\u0431\u043b\u0438\u043a\u0430","common":"\u0410\u0437\u0435\u0440\u0431\u0430\u0439\u0434\u0436\u0430\u043d"}}},"cca2":"AZ","independent":true,"status":"officially-assigned","currency":["AZN"],"capital":["Baku"],"region":"Asia","subregion":"Western Asia","area":86600},
{"name":{"common":"Burundi","official":"Republic of Burundi","native":{"fra":{"official":"R\u00e9publique du Burundi","common":"Burundi"},"run":{"official":"Republika y'Uburundi ","common":"Uburundi"}}},"cca2":"BI","independent":true,"status":"officially-assigned","currency":["BIF"],"capital":["Bujumbura"],"region":"Africa","subregion":"Eastern Africa","area":27834},
{"name":{"common":"Belgium","official":"Kingdom of Belgium","native":{"deu":{"official":"K\u00f6nigreich Belgien","common":"Belgien"},"fra":{"official":"Royaume de Belgique","common":"Belgique"},"nld":{"official":"Koninkrijk Belgi\u00eb","common":"Belgi\u00eb"}}},"cca2":"BE","independent":true,"status":"officially-assigned","currency":["EUR"],"capital":["Brussels"],"region":"Europe","subregion":"Western Europe","area":30528},
{"name":{"common":"Benin","official":"Republic of Benin","native":{"fra":{"official":"R\u00e9publique du B\u00e9nin","common":"B\u00e9nin"}}},"cca2":"BJ","independent":true,"status":"officially-assigned","currency":["XOF"],"capital":["Porto-Novo"],"region":"Africa","subregion":"Western Africa","area":112622},
{"name":{"common":"Burkina Faso","official":"Burkina Faso","native":{"fra":{"official":"R\u00e9publique du Burkina","common":"Burkina Faso"}}},"cca2":"BF","independent":true,"status":"officially-assigned","currency":["XOF"],"capital":["Ouagadougou"],"region":"Africa","subregion":"Western Africa","area":272967},
{"name":{"common":"Bangladesh","official":"People's Republic of Bangladesh","native":{"ben":{"official":"\u09ac\u09be\u0982\u09b2\u09be\u09a6\u09c7\u09b6 \u0997\u09a3\u09aa\u09cd\u09b0\u099c\u09be\u09a4\u09a8\u09cd\u09a4\u09cd\u09b0\u09c0","common":"\u09ac\u09be\u0982\u09b2\u09be\u09a6\u09c7\u09b6"}}},"cca2":"BD","independent":true,"status":"officially-assigned","currency":["BDT"],"capital":["Dhaka"],"region":"Asia","subregion":"Southern Asia","area":147570},
{"name":{"common":"Bulgaria","official":"Republic of Bulgaria","native":{"bul":{"official":"\u0420\u0435\u043f\u0443\u0431\u043b\u0438\u043a\u0430 \u0411\u044a\u043b\u0433\u0430\u0440\u0438\u044f","common":"\u0411\u044a\u043b\u0433\u0430\u0440\u0438\u044f"}}},"cca2":"BG","independent":true,"status":"officially-assigned","currency":["BGN"],"capital":["Sofia"],"region":"Europe","subregion":"Eastern Europe","area":110879},
{"name":{"common":"Bahrain","official":"Kingdom of Bahrain","native":{"ara":{"official":"\u0645\u0645\u0644\u0643\u0629 \u0627\u0644\u0628\u062d\u0631\u064a\u0646","common":"\u200f\u0627\u0644\u0628\u062d\u0631\u064a\u0646"}}},"cca2":"BH","independent":true,"status":"officially-assigned","currency":["BHD"],"capital":["Manama"],"region":"Asia","subregion":"Western Asia","area":765},
{"name":{"common":"Bahamas","official":"Commonwealth of the Bahamas","native":{"eng":{"official":"Commonwealth of the Bahamas","common":"Bahamas"}}},"cca2":"BS","independent":true,"status":"officially-assigned","currency":["BSD"],"capital":["Nassau"],"region":"Americas","subregion":"Caribbean","area":13943},
{"name":{"common":"Bosnia and Herzegovina","official":"Bosnia and Herzegovina","native":{"bos":{"official":"Bosna i Hercegovina","common":"Bosna i Hercegovina"},"hrv":{"official":"Bosna i Hercegovina","common":"Bosna i Hercegovina"},"srp":{"official":"\u0411\u043e\u0441\u043da \u0438 \u0425\u0435\u0440\u0446\u0435\u0433\u043e\u0432\u0438\u043d\u0430","common":"\u0411\u043e\u0441\u043da \u0438 \u0425\u0435\u0440\u0446\u0435\u0433\u043e\u0432\u0438\u043d\u0430"}}},"cca2":"BA","independent":true,"status":"officially-assigned","currency":["BAM"],"capital":["Sarajevo"],"region":"Europe","subregion":"Southern Europe","area":51209},
{"name":{"common":"Saint Barth\u00e9lemy","official":"Collectivity of Saint Barth\u00e9lemy","native":{"fra":{"official":"Collectivit\u00e9 de Saint-Barth\u00e9lemy","common":"Saint-Barth\u00e9lemy"}}},"cca2":"BL","independent":false,"status":"officially-assigned","currency":["EUR"],"capital":["Gustavia"],"region":"Americas","subregion":"Caribbean","area":21},
{"name":{"common":"Saint Helena, Ascension and Tristan da Cunha","official":"Saint Helena, Ascension and Tristan da Cunha","native":{"eng":{"official":"Saint Helena, Ascension and Tristan da Cunha","common":"Saint Helena, Ascension and Tristan da Cunha"}}},"cca2":"SH","independent":false,"status":"officially-assigned","currency":["SHP","GBP"],"capital":["Jamestown"],"region":"Africa","subregion":"Western Africa","area":394},
{"name":{"common":"Belarus","official":"Republic of Belarus","native":{"bel":{"official":"\u0420\u044d\u0441\u043f\u0443\u0431\u043b\u0456\u043a\u0430 \u0411\u0435\u043b\u0430\u0440\u0443\u0441\u044c","common":"\u0411\u0435\u043b\u0430\u0440\u0443\u0301\u0441\u044c"},"rus":{"official":"\u0420\u0435\u0441\u043f\u0443\u0431\u043b\u0438\u043a\u0430 \u0411\u0435\u043b\u0430\u0440\u0443\u0441\u044c","common":"\u0411\u0435\u043b\u0430\u0440\u0443\u0441\u044c"}}},"cca2":"BY","independent":true,"status":"officially-assigned","currency":["BYN"],"capital":["Minsk"],"region":"Europe","subregion":"Eastern Europe","area":207600},
{"name":{"common":"Belize","official":"Belize","native":{"bjz":{"official":"Belize","common":"Belize"},"eng":{"official":"Belize","common":"Belize"},"spa":{"official":"Belice","common":"Belice"}}},"cca2":"BZ","independent":true,"status":"officially-assigned","currency":["BZD"],"capital":["Belmopan"],"region":"Americas","subregion":"Central America","area":22966},
{"name":{"common":"Bermuda","official":"Bermuda","native":{"eng":{"official":"Bermuda","common":"Bermuda"}}},"cca2":"BM","independent":false,"status":"officially-assigned","currency":["BMD"],"capital":["Hamilton"],"region":"Americas","subregion":"Northern America","area":54},
{"name":{"common":"Bolivia","official":"Plurinational State of Bolivia","native":{"aym":{"official":"Wuliwya Suyu","common":"Wuliwya"},"grn":{"official":"Tet\u00e3 Vol\u00edvia","common":"Vol\u00edvia"},"que":{"official":"Buliwya Mamallaqta","common":"Buliwya"},"spa":{"official":"Estado Plurinacional de Bolivia","common":"Bolivia"}}},"cca2":"BO","independent":true,"status":"officially-assigned","currency":["BOB","BOV"],"capital":["Sucre"],"region":"Americas","subregion":"South America","area":1098581},
{"name":{"common":"Caribbean Netherlands","official":"Bonaire, Sint Eustatius and Saba","native":{"nld":{"official":"Bonaire, Sint Eustatius en Saba","common":"Caribisch Nederland"},"pap":{"official":"Boneiru, Sint Eustatius y Saba","common":"Boneiru, Sint Eustatius y Saba"}}},"cca2":"BQ","independent":false,"status":"officially-assigned","currency":["USD"],"capital":[],"region":"Americas","subregion":"Caribbean","area":328},
{"name":{"common":"Brazil","official":"Federative Republic of Brazil","native":{"por":{"official":"Rep\u00fablica Federativa do Brasil","common":"Brasil"}}},"cca2":"BR","independent":true,"status":"officially-assigned","currency":["BRL"],"capital":["Bras\u00edlia"],"region":"Americas","subregion":"South America","area":8515767},
{"name":{"common":"Barbados","official":"Barbados","native":{"eng":{"official":"Barbados","common":"Barbados"}}},"cca2":"BB","independent":true,"status":"officially-assigned","currency":["BBD"],"capital":["Bridgetown"],"region":"Americas","subregion":"Caribbean","area":430},
{"name":{"common":"Brunei","official":"Nation of Brunei, Abode of Peace","native":{"msa":{"official":"Nation of Brunei, Abode Damai","common":"Negara Brunei Darussalam"}}},"cca2":"BN","independent":true,"status":"officially-assigned","currency":["BND"],"capital":["Bandar Seri Begawan"],"region":"Asia","subregion":"South-Eastern Asia","area":5765},
{"name":{"common":"Bhutan","official":"Kingdom of Bhutan","native":{"dzo":{"official":"\u0f60\u0f56\u0fb2\u0f74\u0f42\u0f0b\u0f62\u0f92\u0fb1\u0f63\u0f0b\u0f41\u0f56\u0f0b","common":"\u0f60\u0f56\u0fb2\u0f74\u0f42\u0f0b\u0f61\u0f74\u0f63\u0f0b"}}},"cca2":"BT","independent":true,"status":"officially-assigned","currency":["BTN","INR"],"capital":["Thimphu"],"region":"Asia","subregion":"Southern Asia","area":38394},
{"name":{"common":"Bouvet Island","official":"Bouvet Island","native":{"nor":{"official":"Bouvet\u00f8ya","common":"Bouvet\u00f8ya"}}},"cca2":"BV","independent":false,"status":"officially-assigned","currency":["NOK"],"capital":[""],"region":"Antarctic","subregion":"","area":49},
{"name":{"common":"Botswana","official":"Republic of Botswana","native":{"eng":{"official":"Republic of Botswana","common":"Botswana"},"tsn":{"official":"Lefatshe la Botswana","common":"Botswana"}}},"cca2":"BW","independent":true,"status":"officially-assigned","currency":["BWP"],"capital":["Gaborone"],"region":"Africa","subregion":"Southern Africa","area":582000},
{"name":{"common":"Central African Republic","official":"Central African Republic","native":{"fra":{"official":"R\u00e9publique centrafricaine","common":"R\u00e9publique centrafricaine"},"sag":{"official":"K\u00f6d\u00f6r\u00f6s\u00ease t\u00ee B\u00eaafr\u00eeka","common":"B\u00eaafr\u00eeka"}}},"cca2":"CF","independent":true,"status":"officially-assigned","currency":["XAF"],"capital":["Bangui"],"region":"Africa","subregion":"Middle Africa","area":622984},
{"name":{"common":"Canada","official":"Canada","native":{"eng":{"official":"Canada","common":"Canada"},"fra":{"official":"Canada","common":"Canada"}}},"cca2":"CA","independent":true,"status":"officially-assigned","currency":["CAD"],"capital":["Ottawa"],"region":"Americas","subregion":"Northern America","area":9984670},
{"name":{"common":"Cocos (Keeling) Islands","official":"Territory of the Cocos (Keeling) Islands","native":{"eng":{"official":"Territory of the Cocos (Keeling) Islands","common":"Cocos (Keeling) Islands"}}},"cca2":"CC","independent":false,"status":"officially-assigned","currency":["AUD"],"capital":["West Island"],"region":"Oceania","subregion":"Australia and New Zealand","area":14},
{"name":{"common":"Switzerland","official":"Swiss Confederation","native":{"fra":{"official":"Conf\u00e9d\u00e9ration suisse","common":"Suisse"},"gsw":{"official":"Schweizerische Eidgenossenschaft","common":"Schweiz"},"ita":{"official":"Confederazione Svizzera","common":"Svizzera"},"roh":{"official":"Confederaziun svizra","common":"Svizra"}}},"cca2":"CH","independent":true,"status":"officially-assigned","currency":["CHE","CHF","CHW"],"capital":["Bern"],"region":"Europe","subregion":"Western Europe","area":41284},
{"name":{"common":"Chile","official":"Republic of Chile","native":{"spa":{"official":"Rep\u00fablica de Chile","common":"Chile"}}},"cca2":"CL","independent":true,"status":"officially-assigned","currency":["CLF","CLP"],"capital":["Santiago"],"region":"Americas","subregion":"South America","area":756102},
{"name":{"common":"China","official":"People's Republic of China","native":{"zho":{"official":"\u4e2d\u534e\u4eba\u6c11\u5171\u548c\u56fd","common":"\u4e2d\u56fd"}}},"cca2":"CN","independent":true,"status":"officially-assigned","currency":["CNY"],"capital":["Beijing"],"region":"Asia","subregion":"Eastern Asia","area":9706961},
{"name":{"common":"Ivory Coast","official":"Republic of C\u00f4te d'Ivoire","native":{"fra":{"official":"R\u00e9publique de C\u00f4te d'Ivoire","common":"C\u00f4te d'Ivoire"}}},"cca2":"CI","independent":true,"status":"officially-assigned","currency":["XOF"],"capital":["Yamoussoukro"],"region":"Africa","subregion":"Western Africa","area":322463},
{"name":{"common":"Cameroon","official":"Republic of Cameroon","native":{"eng":{"official":"Republic of Cameroon","common":"Cameroon"},"fra":{"official":"R\u00e9publique du Cameroun","common":"Cameroun"}}},"cca2":"CM","independent":true,"status":"officially-assigned","currency":["XAF"],"capital":["Yaound\u00e9"],"region":"Africa","subregion":"Middle Africa","area":475442},
{"name":{"common":"DR Congo","official":"Democratic Republic of the Congo","native":{"fra":{"official":"R\u00e9publique d\u00e9mocratique du Congo","common":"RD Congo"},"kon":{"official":"Repubilika ya Kongo Demokratiki","common":"Repubilika ya Kongo Demokratiki"},"lin":{"official":"Republiki ya Kong\u00f3 Demokratiki","common":"Republiki ya Kong\u00f3 Demokratiki"},"lua":{"official":"Ditunga dia Kongu wa Mungalaata","common":"Ditunga dia Kongu wa Mungalaata"},"swa":{"official":"Jamhuri ya Kidemokrasia ya Kongo","common":"Jamhuri ya Kidemokrasia ya Kongo"}}},"cca2":"CD","independent":true,"status":"officially-assigned","currency":["CDF"],"capital":["Kinshasa"],"region":"Africa","subregion":"Middle Africa","area":2344858},
{"name":{"common":"Republic of the Congo","official":"Republic of the Congo","native":{"fra":{"official":"R\u00e9publique du Congo","common":"R\u00e9publique du Congo"},"kon":{"official":"Repubilika ya Kongo","common":"Repubilika ya Kongo"},"lin":{"official":"Republ\u00edki ya Kong\u00f3","common":"Republ\u00edki ya Kong\u00f3"}}},"cca2":"CG","independent":true,"status":"officially-assigned","currency":["XAF"],"capital":["Brazzaville"],"region":"Africa","subregion":"Middle Africa","area":342000},
{"name":{"common":"Cook Islands","official":"Cook Islands","native":{"eng":{"official":"Cook Islands","common":"Cook Islands"},"rar":{"official":"K\u016bki '\u0100irani","common":"K\u016bki '\u0100irani"}}},"cca2":"CK","independent":false,"status":"officially-assigned","currency":["NZD","CKD"],"capital":["Avarua"],"region":"Oceania","subregion":"Polynesia","area":236},
{"name":{"common":"Colombia","official":"Republic of Colombia","native":{"spa":{"official":"Rep\u00fablica de Colombia","common":"Colombia"}}},"cca2":"CO","independent":true,"status":"officially-assigned","currency":["COP"],"capital":["Bogot\u00e1"],"region":"Americas","subregion":"South America","area":1141748},
{"name":{"common":"Comoros","official":"Union of the Comoros","native":{"ara":{"official":"\u0627\u0644\u0627\u062a\u062d\u0627\u062f \u0627\u0644\u0642\u0645\u0631\u064a","common":"\u0627\u0644\u0642\u0645\u0631\u200e"},"fra":{"official":"Union des Comores","common":"Comores"},"zdj":{"official":"Udzima wa Komori","common":"Komori"}}},"cca2":"KM","independent":true,"status":"officially-assigned","currency":["KMF"],"capital":["Moroni"],"region":"Africa","subregion":"Eastern Africa","area":1862},
{"name":{"common":"Cape Verde","official":"Republic of Cabo Verde","native":{"por":{"official":"Rep\u00fablica de Cabo Verde","common":"Cabo Verde"}}},"cca2":"CV","independent":true,"status":"officially-assigned","currency":["CVE"],"capital":["Praia"],"region":"Africa","subregion":"Western Africa","area":4033},
{"name":{"common":"Costa Rica","official":"Republic of Costa Rica","native":{"spa":{"official":"Rep\u00fablica de Costa Rica","common":"Costa Rica"}}},"cca2":"CR","independent":true,"status":"officially-assigned","currency":["CRC"],"capital":["San Jos\u00e9"],"region":"Americas","subregion":"Central America","area":51100},
{"name":{"common":"Cuba","official":"Republic of Cuba","native":{"spa":{"official":"Rep\u00fablica de Cuba","common":"Cuba"}}},"cca2":"CU","independent":true,"status":"officially-assigned","currency":["CUC","CUP"],"capital":["Havana"],"region":"Americas","subregion":"Caribbean","area":109884},
{"name":{"common":"Cura\u00e7ao","official":"Country of Cura\u00e7ao","native":{"eng":{"official":"Country of Cura\u00e7ao","common":"Cura\u00e7ao"},"nld":{"official":"Land Cura\u00e7ao","common":"Cura\u00e7ao"},"pap":{"official":"Pais K\u00f2rsou","common":"Pais K\u00f2rsou"}}},"cca2":"CW","independent":false,"status":"officially-assigned","currency":["ANG"],"capital":["Willemstad"],"region":"Americas","subregion":"Caribbean","area":444},
{"name":{"common":"Christmas Island","official":"Territory of Christmas Island","native":{"eng":{"official":"Territory of Christmas Island","common":"Christmas Island"}}},"cca2":"CX","independent":false,"status":"officially-assigned","currency":["AUD"],"capital":["Flying Fish Cove"],"region":"Oceania","subregion":"Australia and New Zealand","area":135},
{"name":{"common":"Cayman Islands","official":"Cayman Islands","native":{"eng":{"official":"Cayman Islands","common":"Cayman Islands"}}},"cca2":"KY","independent":false,"status":"officially-assigned","currency":["KYD"],"capital":["George Town"],"region":"Americas","subregion":"Caribbean","area":264},
{"name":{"common":"Cyprus","official":"Republic of Cyprus","native":{"ell":{"official":"\u0394\u03b7\u03bc\u03bf\u03ba\u03c1\u03b1\u03c4\u03af\u03b1 \u03c4\u03b7\u03c2 \u039a\u03cd\u03c0\u03c1\u03bf\u03c2","common":"\u039a\u03cd\u03c0\u03c1\u03bf\u03c2"},"tur":{"official":"K\u0131br\u0131s Cumhuriyeti","common":"K\u0131br\u0131s"}}},"cca2":"CY","independent":true,"status":"officially-assigned","currency":["EUR"],"capital":["Nicosia"],"region":"Europe","subregion":"Eastern Europe","area":9251},
{"name":{"common":"Czechia","official":"Czech Republic","native":{"ces":{"official":"\u010desk\u00e1 republika","common":"\u010cesko"},"slk":{"official":"\u010cesk\u00e1 republika","common":"\u010cesko"}}},"cca2":"CZ","independent":true,"status":"officially-assigned","currency":["CZK"],"capital":["Prague"],"region":"Europe","subregion":"Eastern Europe","area":78865},
{"name":{"common":"Germany","official":"Federal Republic of Germany","native":{"deu":{"official":"Bundesrepublik Deutschland","common":"Deutschland"}}},"cca2":"DE","independent":true,"status":"officially-assigned","currency":["EUR"],"capital":["Berlin"],"region":"Europe","subregion":"Western Europe","area":357114},
{"name":{"common":"Djibouti","official":"Republic of Djibouti","native":{"ara":{"official":"\u062c\u0645\u0647\u0648\u0631\u064a\u0629 \u062c\u064a\u0628\u0648\u062a\u064a","common":"\u062c\u064a\u0628\u0648\u062a\u064a\u200e"},"fra":{"official":"R\u00e9publique de Djibouti","common":"Djibouti"}}},"cca2":"DJ","independent":true,"status":"officially-assigned","currency":["DJF"],"capital":["Djibouti"],"region":"Africa","subregion":"Eastern Africa","area":23200},
{"name":{"common":"Dominica","official":"Commonwealth of Dominica","native":{"eng":{"official":"Commonwealth of Dominica","common":"Dominica"}}},"cca2":"DM","independent":true,"status":"officially-assigned","currency":["XCD"],"capital":["Roseau"],"region":"Americas","subregion":"Caribbean","area":751},
{"name":{"common":"Denmark","official":"Kingdom of Denmark","native":{"dan":{"official":"Kongeriget Danmark","common":"Danmark"}}},"cca2":"DK","independent":true,"status":"officially-assigned","currency":["DKK"],"capital":["Copenhagen"],"region":"Europe","subregion":"Northern Europe","area":43094},
{"name":{"common":"Dominican Republic","official":"Dominican Republic","native":{"spa":{"official":"Rep\u00fablica Dominicana","common":"Rep\u00fablica Dominicana"}}},"cca2":"DO","independent":true,"status":"officially-assigned","currency":["DOP"],"capital":["Santo Domingo"],"region":"Americas","subregion":"Caribbean","area":48671},
{"name":{"common":"Algeria","official":"People's Democratic Republic of Algeria","native":{"ara":{"official":"\u0627\u0644\u062c\u0645\u0647\u0648\u0631\u064a\u0629 \u0627\u0644\u062f\u064a\u0645\u0642\u0631\u0627\u0637\u064a\u0629 \u0627\u0644\u0634\u0639\u0628\u064a\u0629 \u0627\u0644\u062c\u0632\u0627\u0626\u0631\u064a\u0629","common":"\u0627\u0644\u062c\u0632\u0627\u0626\u0631"}}},"cca2":"DZ","independent":true,"status":"officially-assigned","currency":["DZD"],"capital":["Algiers"],"region":"Africa","subregion":"Northern Africa","area":2381741},
{"name":{"common":"Ecuador","official":"Republic of Ecuador","native":{"spa":{"official":"Rep\u00fablica del Ecuador","common":"Ecuador"}}},"cca2":"EC","independent":true,"status":"officially-assigned","currency":["USD"],"capital":["Quito"],"region":"Americas","subregion":"South America","area":276841},
{"name":{"common":"Egypt","official":"Arab Republic of Egypt","native":{"ara":{"official":"\u062c\u0645\u0647\u0648\u0631\u064a\u0629 \u0645\u0635\u0631 \u0627\u0644\u0639\u0631\u0628\u064a\u0629","common":"\u0645\u0635\u0631"}}},"cca2":"EG","independent":true,"status":"officially-assigned","currency":["EGP"],"capital":["Cairo"],"region":"Africa","subregion":"Northern Africa","area":1002450},
{"name":{"common":"Eritrea","official":"State of Eritrea","native":{"ara":{"official":"\u062f\u0648\u0644\u0629 \u0625\u0631\u062a\u0631\u064a\u0627","common":"\u0625\u0631\u062a\u0631\u064a\u0627\u200e"},"eng":{"official":"State of Eritrea","common":"Eritrea"},"tir":{"official":"\u1203\u1308\u1228 \u12a4\u122d\u1275\u122b","common":"\u12a4\u122d\u1275\u122b"}}},"cca2":"ER","independent":true,"status":"officially-assigned","currency":["ERN"],"capital":["Asmara"],"region":"Africa","subregion":"Eastern Africa","area":117600},
{"name":{"common":"Western Sahara","official":"Sahrawi Arab Democratic Republic","native":{"ber":{"official":"Sahrawi Arab Democratic Republic","common":"Western Sahara"},"mey":{"official":"\u0627\u0644\u062c\u0645\u0647\u0648\u0631\u064a\u0629 \u0627\u0644\u0639\u0631\u0628\u064a\u0629 \u0627\u0644\u0635\u062d\u0631\u0627\u0648\u064a\u0629 \u0627\u0644\u062f\u064a\u0645\u0642\u0631\u0627\u0637\u064a\u0629","common":"\u0627\u0644\u0635\u062d\u0631\u0627\u0621 \u0627\u0644\u063a\u0631\u0628\u064a\u0629"},"spa":{"official":"Rep\u00fablica \u00c1rabe Saharaui Democr\u00e1tica","common":"Sahara Occidental"}}},"cca2":"EH","independent":false,"status":"officially-assigned","currency":["MAD","DZD","MRO"],"capital":["El Aai\u00fan"],"region":"Africa","subregion":"Northern Africa","area":266000},
{"name":{"common":"Spain","official":"Kingdom of Spain","native":{"spa":{"official":"Reino de Espa\u00f1a","common":"Espa\u00f1a"}}},"cca2":"ES","independent":true,"status":"officially-assigned","currency":["EUR"],"capital":["Madrid"],"region":"Europe","subregion":"Southern Europe","area":505992},
{"name":{"common":"Estonia","official":"Republic of Estonia","native":{"est":{"official":"Eesti Vabariik","common":"Eesti"}}},"cca2":"EE","independent":true,"status":"officially-assigned","currency":["EUR"],"capital":["Tallinn"],"region":"Europe","subregion":"Northern Europe","area":45227},
{"name":{"common":"Ethiopia","official":"Federal Democratic Republic of Ethiopia","native":{"amh":{"official":"\u12e8\u12a2\u1275\u12ee\u1335\u12eb \u134c\u12f4\u122b\u120b\u12ca \u12f2\u121e\u12ad\u122b\u1232\u12eb\u12ca \u122a\u1350\u1265\u120a\u12ad","common":"\u12a2\u1275\u12ee\u1335\u12eb"}}},"cca2":"ET","independent":true,"status":"officially-assigned","currency":["ETB"],"capital":["Addis Ababa"],"region":"Africa","subregion":"Eastern Africa","area":1104300},
{"name":{"common":"Finland","official":"Republic of Finland","native":{"fin":{"official":"Suomen tasavalta","common":"Suomi"},"swe":{"official":"Republiken Finland","common":"Finland"}}},"cca2":"FI","independent":true,"status":"officially-assigned","currency":["EUR"],"capital":["Helsinki"],"region":"Europe","subregion":"Northern Europe","area":338424},
{"name":{"common":"Fiji","official":"Republic of Fiji","native":{"eng":{"official":"Republic of Fiji","common":"Fiji"},"fij":{"official":"Matanitu Tugalala o Viti","common":"Viti"},"hif":{"official":"\u0930\u093f\u092a\u092c\u094d\u0932\u093f\u0915 \u0911\u092b \u092b\u0940\u091c\u0940","common":"\u092b\u093f\u091c\u0940"}}},"cca2":"FJ","independent":true,"status":"officially-assigned","currency":["FJD"],"capital":["Suva"],"region":"Oceania","subregion":"Melanesia","area":18272},
{"name":{"common":"Falkland Islands","official":"Falkland Islands","native":{"eng":{"official":"Falkland Islands","common":"Falkland Islands"}}},"cca2":"FK","independent":false,"status":"officially-assigned","currency":["FKP"],"capital":["Stanley"],"region":"Americas","subregion":"South America","area":12173},
{"name":{"common":"France","official":"French Republic","native":{"fra":{"official":"R\u00e9publique fran\u00e7aise","common":"France"}}},"cca2":"FR","independent":true,"status":"officially-assigned","currency":["EUR"],"capital":["Paris"],"region":"Europe","subregion":"Western Europe","area":551695},
{"name":{"common":"Faroe Islands","official":"Faroe Islands","native":{"dan":{"official":"F\u00e6r\u00f8erne","common":"F\u00e6r\u00f8erne"},"fao":{"official":"F\u00f8royar","common":"F\u00f8royar"}}},"cca2":"FO","independent":false,"status":"officially-assigned","currency":["DKK"],"capital":["T\u00f3rshavn"],"region":"Europe","subregion":"Northern Europe","area":1393},
{"name":{"common":"Micronesia","official":"Federated States of Micronesia","native":{"eng":{"official":"Federated States of Micronesia","common":"Micronesia"}}},"cca2":"FM","independent":true,"status":"officially-assigned","currency":["USD"],"capital":["Palikir"],"region":"Oceania","subregion":"Micronesia","area":702},
{"name":{"common":"Gabon","official":"Gabonese Republic","native":{"fra":{"official":"R\u00e9publique gabonaise","common":"Gabon"}}},"cca2":"GA","independent":true,"status":"officially-assigned","currency":["XAF"],"capital":["Libreville"],"region":"Africa","subregion":"Middle Africa","area":267668},
{"name":{"common":"United Kingdom","official":"United Kingdom of Great Britain and Northern Ireland","native":{"eng":{"official":"United Kingdom of Great Britain and Northern Ireland","common":"United Kingdom"}}},"cca2":"GB","independent":true,"status":"officially-assigned","currency":["GBP"],"capital":["London"],"region":"Europe","subregion":"Northern Europe","area":242900},
{"name":{"common":"Georgia","official":"Georgia","native":{"kat":{"official":"\u10e1\u10d0\u10e5\u10d0\u10e0\u10d7\u10d5\u10d4\u10da\u10dd","common":"\u10e1\u10d0\u10e5\u10d0\u10e0\u10d7\u10d5\u10d4\u10da\u10dd"}}},"cca2":"GE","independent":true,"status":"officially-assigned","currency":["GEL"],"capital":["Tbilisi"],"region":"Asia","subregion":"Western Asia","area":69700},
{"name":{"common":"Guernsey","official":"Bailiwick of Guernsey","native":{"eng":{"official":"Bailiwick of Guernsey","common":"Guernsey"},"fra":{"official":"Bailliage de Guernesey","common":"Guernesey"},"nfr":{"official":"Dg\u00e8rn\u00e9siais","common":"Dg\u00e8rn\u00e9siais"}}},"cca2":"GG","independent":false,"status":"officially-assigned","currency":["GBP"],"capital":["St. Peter Port"],"region":"Europe","subregion":"Northern Europe","area":78},
{"name":{"common":"Ghana","official":"Republic of Ghana","native":{"eng":{"official":"Republic of Ghana","common":"Ghana"}}},"cca2":"GH","independent":true,"status":"officially-assigned","currency":["GHS"],"capital":["Accra"],"region":"Africa","subregion":"Western Africa","area":238533},
{"name":{"common":"Gibraltar","official":"Gibraltar","native":{"eng":{"official":"Gibraltar","common":"Gibraltar"}}},"cca2":"GI","independent":false,"status":"officially-assigned","currency":["GIP"],"capital":["Gibraltar"],"region":"Europe","subregion":"Southern Europe","area":6},
{"name":{"common":"Guinea","official":"Republic of Guinea","native":{"fra":{"official":"R\u00e9publique de Guin\u00e9e","common":"Guin\u00e9e"}}},"cca2":"GN","independent":true,"status":"officially-assigned","currency":["GNF"],"capital":["Conakry"],"region":"Africa","subregion":"Western Africa","area":245857},
{"name":{"common":"Guadeloupe","official":"Guadeloupe","native":{"fra":{"official":"Guadeloupe","common":"Guadeloupe"}}},"cca2":"GP","independent":false,"status":"officially-assigned","currency":["EUR"],"capital":["Basse-Terre"],"region":"Americas","subregion":"Caribbean","area":1628},
{"name":{"common":"Gambia","official":"Republic of the Gambia","native":{"eng":{"official":"Republic of the Gambia","common":"Gambia"}}},"cca2":"GM","independent":true,"status":"officially-assigned","currency":["GMD"],"capital":["Banjul"],"region":"Africa","subregion":"Western Africa","area":10689},
{"name":{"common":"Guinea-Bissau","official":"Republic of Guinea-Bissau","native":{"por":{"official":"Rep\u00fablica da Guin\u00e9-Bissau","common":"Guin\u00e9-Bissau"},"pov":{"official":"Rep\u00fablica da Guin\u00e9-Bissau","common":"Guin\u00e9-Bissau"}}},"cca2":"GW","independent":true,"status":"officially-assigned","currency":["XOF"],"capital":["Bissau"],"region":"Africa","subregion":"Western Africa","area":36125},
{"name":{"common":"Equatorial Guinea","official":"Republic of Equatorial Guinea","native":{"fra":{"official":"R\u00e9publique de la Guin\u00e9e \u00c9quatoriale","common":"Guin\u00e9e \u00e9quatoriale"},"por":{"official":"Rep\u00fablica da Guin\u00e9 Equatorial","common":"Guin\u00e9 Equatorial"},"spa":{"official":"Rep\u00fablica de Guinea Ecuatorial","common":"Guinea Ecuatorial"}}},"cca2":"GQ","independent":true,"status":"officially-assigned","currency":["XAF"],"capital":["Malabo"],"region":"Africa","subregion":"Middle Africa","area":28051},
{"name":{"common":"Greece","official":"Hellenic Republic","native":{"ell":{"official":"\u0395\u03bb\u03bb\u03b7\u03bd\u03b9\u03ba\u03ae \u0394\u03b7\u03bc\u03bf\u03ba\u03c1\u03b1\u03c4\u03af\u03b1","common":"\u0395\u03bb\u03bb\u03ac\u03b4\u03b1"}}},"cca2":"GR","independent":true,"status":"officially-assigned","currency":["EUR"],"capital":["Athens"],"region":"Europe","subregion":"Southern Europe","area":131990},
{"name":{"common":"Grenada","official":"Grenada","native":{"eng":{"official":"Grenada","common":"Grenada"}}},"cca2":"GD","independent":true,"status":"officially-assigned","currency":["XCD"],"capital":["St. George's"],"region":"Americas","subregion":"Caribbean","area":344},
{"name":{"common":"Greenland","official":"Greenland","native":{"kal":{"official":"Kalaallit Nunaat","common":"Kalaallit Nunaat"}}},"cca2":"GL","independent":false,"status":"officially-assigned","currency":["DKK"],"capital":["Nuuk"],"region":"Americas","subregion":"Northern America","area":2166086},
{"name":{"common":"Guatemala","official":"Republic of Guatemala","native":{"spa":{"official":"Rep\u00fablica de Guatemala","common":"Guatemala"}}},"cca2":"GT","independent":true,"status":"officially-assigned","currency":["GTQ"],"capital":["Guatemala City"],"region":"Americas","subregion":"Central America","area":108889},
{"name":{"common":"French Guiana","official":"Guiana","native":{"fra":{"official":"Guyane","common":"Guyane fran\u00e7aise"}}},"cca2":"GF","independent":false,"status":"officially-assigned","currency":["EUR"],"capital":["Cayenne"],"region":"Americas","subregion":"South America","area":83534},
{"name":{"common":"Guam","official":"Guam","native":{"cha":{"official":"Gu\u00e5h\u00e5n","common":"Gu\u00e5h\u00e5n"},"eng":{"official":"Guam","common":"Guam"},"spa":{"official":"Guam","common":"Guam"}}},"cca2":"GU","independent":false,"status":"officially-assigned","currency":["USD"],"capital":["Hag\u00e5t\u00f1a"],"region":"Oceania","subregion":"Micronesia","area":549},
{"name":{"common":"Guyana","official":"Co-operative Republic of Guyana","native":{"eng":{"official":"Co-operative Republic of Guyana","common":"Guyana"}}},"cca2":"GY","independent":true,"status":"officially-assigned","currency":["GYD"],"capital":["Georgetown"],"region":"Americas","subregion":"South America","area":214969},
{"name":{"common":"Hong Kong","official":"Hong Kong Special Administrative Region of the People's Republic of China","native":{"eng":{"official":"Hong Kong Special Administrative Region of the People's Republic of China","common":"Hong Kong"},"zho":{"official":"\u4e2d\u534e\u4eba\u6c11\u5171\u548c\u56fd\u9999\u6e2f\u7279\u522b\u884c\u653f\u533a","common":"\u9999\u6e2f"}}},"cca2":"HK","independent":false,"status":"officially-assigned","currency":["HKD"],"capital":["City of Victoria"],"region":"Asia","subregion":"Eastern Asia","area":1104},
{"name":{"common":"Heard Island and McDonald Islands","official":"Heard Island and McDonald Islands","native":{"eng":{"official":"Heard Island and McDonald Islands","common":"Heard Island and McDonald Islands"}}},"cca2":"HM","independent":false,"status":"officially-assigned","currency":["AUD"],"capital":[""],"region":"Antarctic","subregion":"","area":412},
{"name":{"common":"Honduras","official":"Republic of Honduras","native":{"spa":{"official":"Rep\u00fablica de Honduras","common":"Honduras"}}},"cca2":"HN","independent":true,"status":"officially-assigned","currency":["HNL"],"capital":["Tegucigalpa"],"region":"Americas","subregion":"Central America","area":112492},
{"name":{"common":"Croatia","official":"Republic of Croatia","native":{"hrv":{"official":"Republika Hrvatska","common":"Hrvatska"}}},"cca2":"HR","independent":true,"status":"officially-assigned","currency":["HRK"],"capital":["Zagreb"],"region":"Europe","subregion":"Southern Europe","area":56594},
{"name":{"common":"Haiti","official":"Republic of Haiti","native":{"fra":{"official":"R\u00e9publique d'Ha\u00efti","common":"Ha\u00efti"},"hat":{"official":"Repiblik Ayiti","common":"Ayiti"}}},"cca2":"HT","independent":true,"status":"officially-assigned","currency":["HTG","USD"],"capital":["Port-au-Prince"],"region":"Americas","subregion":"Caribbean","area":27750},
{"name":{"common":"Hungary","official":"Hungary","native":{"hun":{"official":"Magyarorsz\u00e1g","common":"Magyarorsz\u00e1g"}}},"cca2":"HU","independent":true,"status":"officially-assigned","currency":["HUF"],"capital":["Budapest"],"region":"Europe","subregion":"Eastern Europe","area":93028},
{"name":{"common":"Indonesia","official":"Republic of Indonesia","native":{"ind":{"official":"Republik Indonesia","common":"Indonesia"}}},"cca2":"ID","independent":true,"status":"officially-assigned","currency":["IDR"],"capital":["Jakarta"],"region":"Asia","subregion":"South-Eastern Asia","area":1904569},
{"name":{"common":"Isle of Man","official":"Isle of Man","native":{"eng":{"official":"Isle of Man","common":"Isle of Man"},"glv":{"official":"Ellan Vannin or Mannin","common":"Mannin"}}},"cca2":"IM","independent":false,"status":"officially-assigned","currency":["GBP"],"capital":["Douglas"],"region":"Europe","subregion":"Northern Europe","area":572},
{"name":{"common":"India","official":"Republic of India","native":{"eng":{"official":"Republic of India","common":"India"},"hin":{"official":"\u092d\u093e\u0930\u0924 \u0917\u0923\u0930\u093e\u091c\u094d\u092f","common":"\u092d\u093e\u0930\u0924"},"tam":{"official":"\u0b87\u0ba8\u0bcd\u0ba4\u0bbf\u0baf\u0b95\u0bcd \u0b95\u0bc1\u0b9f\u0bbf\u0baf\u0bb0\u0b9a\u0bc1","common":"\u0b87\u0ba8\u0bcd\u0ba4\u0bbf\u0baf\u0bbe"}}},"cca2":"IN","independent":true,"status":"officially-assigned","currency":["INR"],"capital":["New Delhi"],"region":"Asia","subregion":"Southern Asia","area":3287590},
{"name":{"common":"British Indian Ocean Territory","official":"British Indian Ocean Territory","native":{"eng":{"official":"British Indian Ocean Territory","common":"British Indian Ocean Territory"}}},"cca2":"IO","independent":false,"status":"officially-assigned","currency":["USD"],"capital":["Diego Garcia"],"region":"Africa","subregion":"Eastern Africa","area":60},
{"name":{"common":"Ireland","official":"Republic of Ireland","native":{"eng":{"official":"Republic of Ireland","common":"Ireland"},"gle":{"official":"Poblacht na h\u00c9ireann","common":"\u00c9ire"}}},"cca2":"IE","independent":true,"status":"officially-assigned","currency":["EUR"],"capital":["Dublin"],"region":"Europe","subregion":"Northern Europe","area":70273},
{"name":{"common":"Iran","official":"Islamic Republic of Iran","native":{"fas":{"official":"\u062c\u0645\u0647\u0648\u0631\u06cc \u0627\u0633\u0644\u0627\u0645\u06cc \u0627\u06cc\u0631\u0627\u0646","common":"\u0627\u06cc\u0631\u0627\u0646"}}},"cca2":"IR","independent":true,"status":"officially-assigned","currency":["IRR"],"capital":["Tehran"],"region":"Asia","subregion":"Southern Asia","area":1648195},
{"name":{"common":"Iraq","official":"Republic of Iraq","native":{"ara":{"official":"\u062c\u0645\u0647\u0648\u0631\u064a\u0629 \u0627\u0644\u0639\u0631\u0627\u0642","common":"\u0627\u0644\u0639\u0631\u0627\u0642"},"arc":{"official":"\u0729\u0718\u073c\u071b\u0722\u0735\u0710 \u0710\u071d\u073c\u072a\u0732\u0729","common":"\u0729\u0718\u073c\u071b\u0722\u0735\u0710"},"ckb":{"official":"\u06a9\u06c6\u0645\u0627\u0631\u06cc \u0639\u06ce\u0631\u0627\u0642","common":"\u06a9\u06c6\u0645\u0627\u0631\u06cc"}}},"cca2":"IQ","independent":true,"status":"officially-assigned","currency":["IQD"],"capital":["Baghdad"],"region":"Asia","subregion":"Western Asia","area":438317},
{"name":{"common":"Iceland","official":"Iceland","native":{"isl":{"official":"\u00cdsland","common":"\u00cdsland"}}},"cca2":"IS","independent":true,"status":"officially-assigned","currency":["ISK"],"capital":["Reykjavik"],"region":"Europe","subregion":"Northern Europe","area":103000},
{"name":{"common":"Israel","official":"State of Israel","native":{"ara":{"official":"\u062f\u0648\u0644\u0629 \u0625\u0633\u0631\u0627\u0626\u064a\u0644","common":"\u0625\u0633\u0631\u0627\u0626\u064a\u0644"},"heb":{"official":"\u05de\u05d3\u05d9\u05e0\u05ea \u05d9\u05e9\u05e8\u05d0\u05dc","common":"\u05d9\u05e9\u05e8\u05d0\u05dc"}}},"cca2":"IL","independent":true,"status":"officially-assigned","currency":["ILS"],"capital":["Jerusalem"],"region":"Asia","subregion":"Western Asia","area":20770},
{"name":{"common":"Italy","official":"Italian Republic","native":{"ita":{"official":"Repubblica italiana","common":"Italia"}}},"cca2":"IT","independent":true,"status":"officially-assigned","currency":["EUR"],"capital":["Rome"],"region":"Europe","subregion":"Southern Europe","area":301336},
{"name":{"common":"Jamaica","official":"Jamaica","native":{"eng":{"official":"Jamaica","common":"Jamaica"},"jam":{"official":"Jamaica","common":"Jamaica"}}},"cca2":"JM","independent":true,"status":"officially-assigned","currency":["JMD"],"capital":["Kingston"],"region":"Americas","subregion":"Caribbean","area":10991},
{"name":{"common":"Jersey","official":"Bailiwick of Jersey","native":{"eng":{"official":"Bailiwick of Jersey","common":"Jersey"},"fra":{"official":"Bailliage de Jersey","common":"Jersey"},"nrf":{"official":"Bailliage d\u00e9 J\u00e8rri","common":"J\u00e8rri"}}},"cca2":"JE","independent":false,"status":"officially-assigned","currency":["GBP"],"capital":["Saint Helier"],"region":"Europe","subregion":"Northern Europe","area":116},
{"name":{"common":"Jordan","official":"Hashemite Kingdom of Jordan","native":{"ara":{"official":"\u0627\u0644\u0645\u0645\u0644\u0643\u0629 \u0627\u0644\u0623\u0631\u062f\u0646\u064a\u0629 \u0627\u0644\u0647\u0627\u0634\u0645\u064a\u0629","common":"\u0627\u0644\u0623\u0631\u062f\u0646"}}},"cca2":"JO","independent":true,"status":"officially-assigned","currency":["JOD"],"capital":["Amman"],"region":"Asia","subregion":"Western Asia","area":89342},
{"name":{"common":"Japan","official":"Japan","native":{"jpn":{"official":"\u65e5\u672c","common":"\u65e5\u672c"}}},"cca2":"JP","independent":true,"status":"officially-assigned","currency":["JPY"],"capital":["Tokyo"],"region":"Asia","subregion":"Eastern Asia","area":377930},
{"name":{"common":"Kazakhstan","official":"Republic of Kazakhstan","native":{"kaz":{"official":"\u049a\u0430\u0437\u0430\u049b\u0441\u0442\u0430\u043d \u0420\u0435\u0441\u043f\u0443\u0431\u043b\u0438\u043a\u0430\u0441\u044b","common":"\u049a\u0430\u0437\u0430\u049b\u0441\u0442\u0430\u043d"},"rus":{"official":"\u0420\u0435\u0441\u043f\u0443\u0431\u043b\u0438\u043a\u0430 \u041a\u0430\u0437\u0430\u0445\u0441\u0442\u0430\u043d","common":"\u041a\u0430\u0437\u0430\u0445\u0441\u0442\u0430\u043d"}}},"cca2":"KZ","independent":true,"status":"officially-assigned","currency":["KZT"],"capital":["Astana"],"region":"Asia","subregion":"Central Asia","area":2724900},
{"name":{"common":"Kenya","official":"Republic of Kenya","native":{"eng":{"official":"Republic of Kenya","common":"Kenya"},"swa":{"official":"Republic of Kenya","common":"Kenya"}}},"cca2":"KE","independent":true,"status":"officially-assigned","currency":["KES"],"capital":["Nairobi"],"region":"Africa","subregion":"Eastern Africa","area":580367},
{"name":{"common":"Kyrgyzstan","official":"Kyrgyz Republic","native":{"kir":{"official":"\u041a\u044b\u0440\u0433\u044b\u0437 \u0420\u0435\u0441\u043f\u0443\u0431\u043b\u0438\u043a\u0430\u0441\u044b","common":"\u041a\u044b\u0440\u0433\u044b\u0437\u0441\u0442\u0430\u043d"},"rus":{"official":"\u041a\u044b\u0440\u0433\u044b\u0437\u0441\u043a\u0430\u044f \u0420\u0435\u0441\u043f\u0443\u0431\u043b\u0438\u043a\u0430","common":"\u041a\u0438\u0440\u0433\u0438\u0437\u0438\u044f"}}},"cca2":"KG","independent":true,"status":"officially-assigned","currency":["KGS"],"capital":["Bishkek"],"region":"Asia","subregion":"Central Asia","area":199951},
{"name":{"common":"Cambodia","official":"Kingdom of Cambodia","native":{"khm":{"official":"\u1796\u17d2\u179a\u17c7\u179a\u17b6\u1787\u17b6\u178e\u17b6\u1785\u1780\u17d2\u179a\u1780\u1798\u17d2\u1796\u17bb\u1787\u17b6","common":"K\u00e2mp\u016dch\u00e9a"}}},"cca2":"KH","independent":true,"status":"officially-assigned","currency":["KHR"],"capital":["Phnom Penh"],"region":"Asia","subregion":"South-Eastern Asia","area":181035},
{"name":{"common":"Kiribati","official":"Independent and Sovereign Republic of Kiribati","native":{"eng":{"official":"Independent and Sovereign Republic of Kiribati","common":"Kiribati"},"gil":{"official":"Ribaberiki Kiribati","common":"Kiribati"}}},"cca2":"KI","independent":true,"status":"officially-assigned","currency":["AUD"],"capital":["South Tarawa"],"region":"Oceania","subregion":"Micronesia","area":811},
{"name":{"common":"Saint Kitts and Nevis","official":"Federation of Saint Christopher and Nevisa","native":{"eng":{"official":"Federation of Saint Christopher and Nevisa","common":"Saint Kitts and Nevis"}}},"cca2":"KN","independent":true,"status":"officially-assigned","currency":["XCD"],"capital":["Basseterre"],"region":"Americas","subregion":"Caribbean","area":261},
{"name":{"common":"South Korea","official":"Republic of Korea","native":{"kor":{"official":"\ud55c\uad6d","common":"\ub300\ud55c\ubbfc\uad6d"}}},"cca2":"KR","independent":true,"status":"officially-assigned","currency":["KRW"],"capital":["Seoul"],"region":"Asia","subregion":"Eastern Asia","area":100210},
{"name":{"common":"Kosovo","official":"Republic of Kosovo","native":{"sqi":{"official":"Republika e Kosov\u00ebs","common":"Kosova"},"srp":{"official":"\u0420\u0435\u043f\u0443\u0431\u043b\u0438\u043a\u0430 \u041a\u043e\u0441\u043e\u0432\u043e","common":"\u041a\u043e\u0441\u043e\u0432\u043e"}}},"cca2":"XK","independent":null,"status":"user-assigned","currency":["EUR"],"capital":["Pristina"],"region":"Europe","subregion":"Eastern Europe","area":10908},
{"name":{"common":"Kuwait","official":"State of Kuwait","native":{"ara":{"official":"\u062f\u0648\u0644\u0629 \u0627\u0644\u0643\u0648\u064a\u062a","common":"\u0627\u0644\u0643\u0648\u064a\u062a"}}},"cca2":"KW","independent":true,"status":"officially-assigned","currency":["KWD"],"capital":["Kuwait City"],"region":"Asia","subregion":"Western Asia","area":17818},
{"name":{"common":"Laos","official":"Lao People's Democratic Republic","native":{"lao":{"official":"\u0eaa\u0eb2\u0e97\u0eb2\u0ea5\u0eb0\u0e99\u0eb0 \u0e8a\u0eb2\u0e97\u0eb4\u0e9b\u0eb0\u0ec4\u0e95 \u0e84\u0ebb\u0e99\u0ea5\u0eb2\u0ea7 \u0e82\u0ead\u0e87","common":"\u0eaa\u0e9b\u0e9b\u0ea5\u0eb2\u0ea7"}}},"cca2":"LA","independent":true,"status":"officially-assigned","currency":["LAK"],"capital":["Vientiane"],"region":"Asia","subregion":"South-Eastern Asia","area":236800},
{"name":{"common":"Lebanon","official":"Lebanese Republic","native":{"ara":{"official":"\u0627\u0644\u062c\u0645\u0647\u0648\u0631\u064a\u0629 \u0627\u0644\u0644\u0628\u0646\u0627\u0646\u064a\u0629","common":"\u0644\u0628\u0646\u0627\u0646"},"fra":{"official":"R\u00e9publique libanaise","common":"Liban"}}},"cca2":"LB","independent":true,"status":"officially-assigned","currency":["LBP"],"capital":["Beirut"],"region":"Asia","subregion":"Western Asia","area":10452},
{"name":{"common":"Liberia","official":"Republic of Liberia","native":{"eng":{"official":"Republic of Liberia","common":"Liberia"}}},"cca2":"LR","independent":true,"status":"officially-assigned","currency":["LRD"],"capital":["Monrovia"],"region":"Africa","subregion":"Western Africa","area":111369},
{"name":{"common":"Libya","official":"State of Libya","native":{"ara":{"official":"\u0627\u0644\u062f\u0648\u0644\u0629 \u0644\u064a\u0628\u064a\u0627","common":"\u200f\u0644\u064a\u0628\u064a\u0627"}}},"cca2":"LY","independent":true,"status":"officially-assigned","currency":["LYD"],"capital":["Tripoli"],"region":"Africa","subregion":"Northern Africa","area":1759540},
{"name":{"common":"Saint Lucia","official":"Saint Lucia","native":{"eng":{"official":"Saint Lucia","common":"Saint Lucia"}}},"cca2":"LC","independent":true,"status":"officially-assigned","currency":["XCD"],"capital":["Castries"],"region":"Americas","subregion":"Caribbean","area":616},
{"name":{"common":"Liechtenstein","official":"Principality of Liechtenstein","native":{"deu":{"official":"F\u00fcrstentum Liechtenstein","common":"Liechtenstein"}}},"cca2":"LI","independent":true,"status":"officially-assigned","currency":["CHF"],"capital":["Vaduz"],"region":"Europe","subregion":"Western Europe","area":160},
{"name":{"common":"Sri Lanka","official":"Democratic Socialist Republic of Sri Lanka","native":{"sin":{"official":"\u0dc1\u0dca\u200d\u0dbb\u0dd3 \u0dbd\u0d82\u0d9a\u0dcf \u0db4\u0dca\u200d\u0dbb\u0da2\u0dcf\u0dad\u0dcf\u0db1\u0dca\u0dad\u0dca\u200d\u0dbb\u0dd2\u0d9a \u0dc3\u0db8\u0dcf\u0da2\u0dc0\u0dcf\u0daf\u0dd3 \u0da2\u0db1\u0dbb\u0da2\u0dba","common":"\u0dc1\u0dca\u200d\u0dbb\u0dd3 \u0dbd\u0d82\u0d9a\u0dcf\u0dc0"},"tam":{"official":"\u0b87\u0bb2\u0b99\u0bcd\u0b95\u0bc8 \u0b9a\u0ba9\u0ba8\u0bbe\u0baf\u0b95 \u0b9a\u0bcb\u0b9a\u0bb2\u0bbf\u0b9a\u0b95\u0bcd \u0b95\u0bc1\u0b9f\u0bbf\u0baf\u0bb0\u0b9a\u0bc1","common":"\u0b87\u0bb2\u0b99\u0bcd\u0b95\u0bc8"}}},"cca2":"LK","independent":true,"status":"officially-assigned","currency":["LKR"],"capital":["Colombo"],"region":"Asia","subregion":"Southern Asia","area":65610},
{"name":{"common":"Lesotho","official":"Kingdom of Lesotho","native":{"eng":{"official":"Kingdom of Lesotho","common":"Lesotho"},"sot":{"official":"Kingdom of Lesotho","common":"Lesotho"}}},"cca2":"LS","independent":true,"status":"officially-assigned","currency":["LSL","ZAR"],"capital":["Maseru"],"region":"Africa","subregion":"Southern Africa","area":30355},
{"name":{"common":"Lithuania","official":"Republic of Lithuania","native":{"lit":{"official":"Lietuvos Respublikos","common":"Lietuva"}}},"cca2":"LT","independent":true,"status":"officially-assigned","currency":["EUR"],"capital":["Vilnius"],"region":"Europe","subregion":"Northern Europe","area":65300},
{"name":{"common":"Luxembourg","official":"Grand Duchy of Luxembourg","native":{"deu":{"official":"Gro\u00dfherzogtum Luxemburg","common":"Luxemburg"},"fra":{"official":"Grand-Duch\u00e9 de Luxembourg","common":"Luxembourg"},"ltz":{"official":"Groussherzogtum L\u00ebtzebuerg","common":"L\u00ebtzebuerg"}}},"cca2":"LU","independent":true,"status":"officially-assigned","currency":["EUR"],"capital":["Luxembourg"],"region":"Europe","subregion":"Western Europe","area":2586},
{"name":{"common":"Latvia","official":"Republic of Latvia","native":{"lav":{"official":"Latvijas Republikas","common":"Latvija"}}},"cca2":"LV","independent":true,"status":"officially-assigned","currency":["EUR"],"capital":["Riga"],"region":"Europe","subregion":"Northern Europe","area":64559},
{"name":{"common":"Macau","official":"Macao Special Administrative Region of the People's Republic of China","native":{"por":{"official":"Regi\u00e3o Administrativa Especial de Macau da Rep\u00fablica Popular da China","common":"Macau"},"zho":{"official":"\u4e2d\u534e\u4eba\u6c11\u5171\u548c\u56fd\u6fb3\u95e8\u7279\u522b\u884c\u653f\u533a","common":"\u6fb3\u95e8"}}},"cca2":"MO","independent":false,"status":"officially-assigned","currency":["MOP"],"capital":[""],"region":"Asia","subregion":"Eastern Asia","area":30},
{"name":{"common":"Saint Martin","official":"Saint Martin","native":{"fra":{"official":"Saint-Martin","common":"Saint-Martin"}}},"cca2":"MF","independent":false,"status":"officially-assigned","currency":["EUR"],"capital":["Marigot"],"region":"Americas","subregion":"Caribbean","area":53},
{"name":{"common":"Morocco","official":"Kingdom of Morocco","native":{"ara":{"official":"\u0627\u0644\u0645\u0645\u0644\u0643\u0629 \u0627\u0644\u0645\u063a\u0631\u0628\u064a\u0629","common":"\u0627\u0644\u0645\u063a\u0631\u0628"},"ber":{"official":"\u2d5c\u2d30\u2d33\u2d4d\u2d37\u2d49\u2d5c \u2d4f \u2d4d\u2d4e\u2d56\u2d54\u2d49\u2d31","common":"\u2d4d\u2d4e\u2d30\u2d56\u2d54\u2d49\u2d31"}}},"cca2":"MA","independent":true,"status":"officially-assigned","currency":["MAD"],"capital":["Rabat"],"region":"Africa","subregion":"Northern Africa","area":446550},
{"name":{"common":"Monaco","official":"Principality of Monaco","native":{"fra":{"official":"Principaut\u00e9 de Monaco","common":"Monaco"}}},"cca2":"MC","independent":true,"status":"officially-assigned","currency":["EUR"],"capital":["Monaco"],"region":"Europe","subregion":"Western Europe","area":2.02},
{"name":{"common":"Moldova","official":"Republic of Moldova","native":{"ron":{"official":"Republica Moldova","common":"Moldova"}}},"cca2":"MD","independent":true,"status":"officially-assigned","currency":["MDL"],"capital":["Chi\u0219in\u0103u"],"region":"Europe","subregion":"Eastern Europe","area":33846},
{"name":{"common":"Madagascar","official":"Republic of Madagascar","native":{"fra":{"official":"R\u00e9publique de Madagascar","common":"Madagascar"},"mlg":{"official":"Repoblikan'i Madagasikara","common":"Madagasikara"}}},"cca2":"MG","independent":true,"status":"officially-assigned","currency":["MGA"],"capital":["Antananarivo"],"region":"Africa","subregion":"Eastern Africa","area":587041},
{"name":{"common":"Maldives","official":"Republic of the Maldives","native":{"div":{"official":"\u078b\u07a8\u0788\u07ac\u0780\u07a8\u0783\u07a7\u0787\u07b0\u0796\u07ad\u078e\u07ac \u0796\u07aa\u0789\u07b0\u0780\u07ab\u0783\u07a8\u0787\u07b0\u0794\u07a7","common":"\u078b\u07a8\u0788\u07ac\u0780\u07a8\u0783\u07a7\u0787\u07b0\u0796\u07ad\u078e\u07ac"}}},"cca2":"MV","independent":true,"status":"officially-assigned","currency":["MVR"],"capital":["Mal\u00e9"],"region":"Asia","subregion":"Southern Asia","area":300},
{"name":{"common":"Mexico","official":"United Mexican States","native":{"spa":{"official":"Estados Unidos Mexicanos","common":"M\u00e9xico"}}},"cca2":"MX","independent":true,"status":"officially-assigned","currency":["MXN"],"capital":["Mexico City"],"region":"Americas","subregion":"Northern America","area":1964375},
{"name":{"common":"Marshall Islands","official":"Republic of the Marshall Islands","native":{"eng":{"official":"Republic of the Marshall Islands","common":"Marshall Islands"},"mah":{"official":"Republic of the Marshall Islands","common":"M\u0327aje\u013c"}}},"cca2":"MH","independent":true,"status":"officially-assigned","currency":["USD"],"capital":["Majuro"],"region":"Oceania","subregion":"Micronesia","area":181},
{"name":{"common":"Macedonia","official":"Republic of Macedonia","native":{"mkd":{"official":"\u0420\u0435\u043f\u0443\u0431\u043b\u0438\u043a\u0430 \u041c\u0430\u043a\u0435\u0434\u043e\u043d\u0438\u0458\u0430","common":"\u041c\u0430\u043a\u0435\u0434\u043e\u043d\u0438\u0458\u0430"}}},"cca2":"MK","independent":true,"status":"officially-assigned","currency":["MKD"],"capital":["Skopje"],"region":"Europe","subregion":"Southern Europe","area":25713},
{"name":{"common":"Mali","official":"Republic of Mali","native":{"fra":{"official":"R\u00e9publique du Mali","common":"Mali"}}},"cca2":"ML","independent":true,"status":"officially-assigned","currency":["XOF"],"capital":["Bamako"],"region":"Africa","subregion":"Western Africa","area":1240192},
{"name":{"common":"Malta","official":"Republic of Malta","native":{"eng":{"official":"Republic of Malta","common":"Malta"},"mlt":{"official":"Repubblika ta ' Malta","common":"Malta"}}},"cca2":"MT","independent":true,"status":"officially-assigned","currency":["EUR"],"capital":["Valletta"],"region":"Europe","subregion":"Southern Europe","area":316},
{"name":{"common":"Myanmar","official":"Republic of the Union of Myanmar","native":{"mya":{"official":"\u1015\u103c\u100a\u103a\u1011\u1031\u102c\u1004\u103a\u1005\u102f \u101e\u1019\u1039\u1019\u1010 \u1019\u103c\u1014\u103a\u1019\u102c\u1014\u102d\u102f\u1004\u103a\u1004\u1036\u1010\u1031\u102c\u103a","common":"\u1019\u103c\u1014\u103a\u1019\u102c"}}},"cca2":"MM","independent":true,"status":"officially-assigned","currency":["MMK"],"capital":["Naypyidaw"],"region":"Asia","subregion":"South-Eastern Asia","area":676578},
{"name":{"common":"Montenegro","official":"Montenegro","native":{"srp":{"official":"\u0426\u0440\u043d\u0430 \u0413\u043e\u0440\u0430","common":"\u0426\u0440\u043d\u0430 \u0413\u043e\u0440\u0430"}}},"cca2":"ME","independent":true,"status":"officially-assigned","currency":["EUR"],"capital":["Podgorica"],"region":"Europe","subregion":"Southern Europe","area":13812},
{"name":{"common":"Mongolia","official":"Mongolia","native":{"mon":{"official":"\u041c\u043e\u043d\u0433\u043e\u043b \u0443\u043b\u0441","common":"\u041c\u043e\u043d\u0433\u043e\u043b \u0443\u043b\u0441"}}},"cca2":"MN","independent":true,"status":"officially-assigned","currency":["MNT"],"capital":["Ulan Bator"],"region":"Asia","subregion":"Eastern Asia","area":1564110},
{"name":{"common":"Northern Mariana Islands","official":"Commonwealth of the Northern Mariana Islands","native":{"cal":{"official":"Commonwealth of the Northern Mariana Islands","common":"Northern Mariana Islands"},"cha":{"official":"Sankattan Siha Na Islas Mari\u00e5nas","common":"Na Islas Mari\u00e5nas"},"eng":{"official":"Commonwealth of the Northern Mariana Islands","common":"Northern Mariana Islands"}}},"cca2":"MP","independent":false,"status":"officially-assigned","currency":["USD"],"capital":["Saipan"],"region":"Oceania","subregion":"Micronesia","area":464},
{"name":{"common":"Mozambique","official":"Republic of Mozambique","native":{"por":{"official":"Rep\u00fablica de Mo\u00e7ambique","common":"Mo\u00e7ambique"}}},"cca2":"MZ","independent":true,"status":"officially-assigned","currency":["MZN"],"capital":["Maputo"],"region":"Africa","subregion":"Eastern Africa","area":801590},
{"name":{"common":"Mauritania","official":"Islamic Republic of Mauritania","native":{"ara":{"official":"\u0627\u0644\u062c\u0645\u0647\u0648\u0631\u064a\u0629 \u0627\u0644\u0625\u0633\u0644\u0627\u0645\u064a\u0629 \u0627\u0644\u0645\u0648\u0631\u064a\u062a\u0627\u0646\u064a\u0629","common":"\u0645\u0648\u0631\u064a\u062a\u0627\u0646\u064a\u0627"}}},"cca2":"MR","independent":true,"status":"officially-assigned","currency":["MRO"],"capital":["Nouakchott"],"region":"Africa","subregion":"Western Africa","area":1030700},
{"name":{"common":"Montserrat","official":"Montserrat","native":{"eng":{"official":"Montserrat","common":"Montserrat"}}},"cca2":"MS","independent":false,"status":"officially-assigned","currency":["XCD"],"capital":["Plymouth"],"region":"Americas","subregion":"Caribbean","area":102},
{"name":{"common":"Martinique","official":"Martinique","native":{"fra":{"official":"Martinique","common":"Martinique"}}},"cca2":"MQ","independent":false,"status":"officially-assigned","currency":["EUR"],"capital":["Fort-de-France"],"region":"Americas","subregion":"Caribbean","area":1128},
{"name":{"common":"Mauritius","official":"Republic of Mauritius","native":{"eng":{"official":"Republic of Mauritius","common":"Mauritius"},"fra":{"official":"R\u00e9publique de Maurice","common":"Maurice"},"mfe":{"official":"Republik Moris","common":"Moris"}}},"cca2":"MU","independent":true,"status":"officially-assigned","currency":["MUR"],"capital":["Port Louis"],"region":"Africa","subregion":"Eastern Africa","area":2040},
{"name":{"common":"Malawi","official":"Republic of Malawi","native":{"eng":{"official":"Republic of Malawi","common":"Malawi"},"nya":{"official":"Chalo cha Malawi, Dziko la Mala\u0175i","common":"Mala\u0175i"}}},"cca2":"MW","independent":true,"status":"officially-assigned","currency":["MWK"],"capital":["Lilongwe"],"region":"Africa","subregion":"Eastern Africa","area":118484},
{"name":{"common":"Malaysia","official":"Malaysia","native":{"eng":{"official":"Malaysia","common":"Malaysia"},"msa":{"official":"\u0645\u0644\u064a\u0633\u064a\u0627","common":"\u0645\u0644\u064a\u0633\u064a\u0627"}}},"cca2":"MY","independent":true,"status":"officially-assigned","currency":["MYR"],"capital":["Kuala Lumpur"],"region":"Asia","subregion":"South-Eastern Asia","area":330803},
{"name":{"common":"Mayotte","official":"Department of Mayotte","native":{"fra":{"official":"D\u00e9partement de Mayotte","common":"Mayotte"}}},"cca2":"YT","independent":false,"status":"officially-assigned","currency":["EUR"],"capital":["Mamoudzou"],"region":"Africa","subregion":"Eastern Africa","area":374},
{"name":{"common":"Namibia","official":"Republic of Namibia","native":{"afr":{"official":"Republiek van Namibi\u00eb","common":"Namibi\u00eb"},"deu":{"official":"Republik Namibia","common":"Namibia"},"eng":{"official":"Republic of Namibia","common":"Namibia"},"her":{"official":"Republic of Namibia","common":"Namibia"},"hgm":{"official":"Republic of Namibia","common":"Namibia"},"kwn":{"official":"Republic of Namibia","common":"Namibia"},"loz":{"official":"Republic of Namibia","common":"Namibia"},"ndo":{"official":"Republic of Namibia","common":"Namibia"},"tsn":{"official":"Lefatshe la Namibia","common":"Namibia"}}},"cca2":"NA","independent":true,"status":"officially-assigned","currency":["NAD","ZAR"],"capital":["Windhoek"],"region":"Africa","subregion":"Southern Africa","area":825615},
{"name":{"common":"New Caledonia","official":"New Caledonia","native":{"fra":{"official":"Nouvelle-Cal\u00e9donie","common":"Nouvelle-Cal\u00e9donie"}}},"cca2":"NC","independent":false,"status":"officially-assigned","currency":["XPF"],"capital":["Noum\u00e9a"],"region":"Oceania","subregion":"Melanesia","area":18575},
{"name":{"common":"Niger","official":"Republic of Niger","native":{"fra":{"official":"R\u00e9publique du Niger","common":"Niger"}}},"cca2":"NE","independent":true,"status":"officially-assigned","currency":["XOF"],"capital":["Niamey"],"region":"Africa","subregion":"Western Africa","area":1267000},
{"name":{"common":"Norfolk Island","official":"Territory of Norfolk Island","native":{"eng":{"official":"Territory of Norfolk Island","common":"Norfolk Island"},"pih":{"official":"Teratri of Norf'k Ailen","common":"Norf'k Ailen"}}},"cca2":"NF","independent":false,"status":"officially-assigned","currency":["AUD"],"capital":["Kingston"],"region":"Oceania","subregion":"Australia and New Zealand","area":36},
{"name":{"common":"Nigeria","official":"Federal Republic of Nigeria","native":{"eng":{"official":"Federal Republic of Nigeria","common":"Nigeria"}}},"cca2":"NG","independent":true,"status":"officially-assigned","currency":["NGN"],"capital":["Abuja"],"region":"Africa","subregion":"Western Africa","area":923768},
{"name":{"common":"Nicaragua","official":"Republic of Nicaragua","native":{"spa":{"official":"Rep\u00fablica de Nicaragua","common":"Nicaragua"}}},"cca2":"NI","independent":true,"status":"officially-assigned","currency":["NIO"],"capital":["Managua"],"region":"Americas","subregion":"Central America","area":130373},
{"name":{"common":"Niue","official":"Niue","native":{"eng":{"official":"Niue","common":"Niue"},"niu":{"official":"Niu\u0113","common":"Niu\u0113"}}},"cca2":"NU","independent":false,"status":"officially-assigned","currency":["NZD"],"capital":["Alofi"],"region":"Oceania","subregion":"Polynesia","area":260},
{"name":{"common":"Netherlands","official":"Netherlands","native":{"nld":{"official":"Nederland","common":"Nederland"}}},"cca2":"NL","independent":true,"status":"officially-assigned","currency":["EUR"],"capital":["Amsterdam"],"region":"Europe","subregion":"Western Europe","area":41850},
{"name":{"common":"Norway","official":"Kingdom of Norway","native":{"nno":{"official":"Kongeriket Noreg","common":"Noreg"},"nob":{"official":"Kongeriket Norge","common":"Norge"},"smi":{"official":"Norgga gonagasriika","common":"Norgga"}}},"cca2":"NO","independent":true,"status":"officially-assigned","currency":["NOK"],"capital":["Oslo"],"region":"Europe","subregion":"Northern Europe","area":323802},
{"name":{"common":"Nepal","official":"Federal Democratic Republic of Nepal","native":{"nep":{"official":"\u0928\u0947\u092a\u093e\u0932 \u0938\u0902\u0918\u0940\u092f \u0932\u094b\u0915\u0924\u093e\u0928\u094d\u0924\u094d\u0930\u093f\u0915 \u0917\u0923\u0924\u0928\u094d\u0924\u094d\u0930","common":"\u0928\u0947\u092a\u093e\u0932"}}},"cca2":"NP","independent":true,"status":"officially-assigned","currency":["NPR"],"capital":["Kathmandu"],"region":"Asia","subregion":"Southern Asia","area":147181},
{"name":{"common":"Nauru","official":"Republic of Nauru","native":{"eng":{"official":"Republic of Nauru","common":"Nauru"},"nau":{"official":"Republic of Nauru","common":"Nauru"}}},"cca2":"NR","independent":true,"status":"officially-assigned","currency":["AUD"],"capital":["Yaren"],"region":"Oceania","subregion":"Micronesia","area":21},
{"name":{"common":"New Zealand","official":"New Zealand","native":{"eng":{"official":"New Zealand","common":"New Zealand"},"mri":{"official":"Aotearoa","common":"Aotearoa"},"nzs":{"official":"New Zealand","common":"New Zealand"}}},"cca2":"NZ","independent":true,"status":"officially-assigned","currency":["NZD"],"capital":["Wellington"],"region":"Oceania","subregion":"Australia and New Zealand","area":270467},
{"name":{"common":"Oman","official":"Sultanate of Oman","native":{"ara":{"official":"\u0633\u0644\u0637\u0646\u0629 \u0639\u0645\u0627\u0646","common":"\u0639\u0645\u0627\u0646"}}},"cca2":"OM","independent":true,"status":"officially-assigned","currency":["OMR"],"capital":["Muscat"],"region":"Asia","subregion":"Western Asia","area":309500},
{"name":{"common":"Pakistan","official":"Islamic Republic of Pakistan","native":{"eng":{"official":"Islamic Republic of Pakistan","common":"Pakistan"},"urd":{"official":"\u0627\u0633\u0644\u0627\u0645\u06cc \u062c\u0645\u06c1\u0648\u0631\u06cc\u06c2 \u067e\u0627\u0643\u0633\u062a\u0627\u0646","common":"\u067e\u0627\u0643\u0633\u062a\u0627\u0646"}}},"cca2":"PK","independent":true,"status":"officially-assigned","currency":["PKR"],"capital":["Islamabad"],"region":"Asia","subregion":"Southern Asia","area":881912},
{"name":{"common":"Panama","official":"Republic of Panama","native":{"spa":{"official":"Rep\u00fablica de Panam\u00e1","common":"Panam\u00e1"}}},"cca2":"PA","independent":true,"status":"officially-assigned","currency":["PAB","USD"],"capital":["Panama City"],"region":"Americas","subregion":"Central America","area":75417},
{"name":{"common":"Pitcairn Islands","official":"Pitcairn Group of Islands","native":{"eng":{"official":"Pitcairn Group of Islands","common":"Pitcairn Islands"}}},"cca2":"PN","independent":false,"status":"officially-assigned","currency":["NZD"],"capital":["Adamstown"],"region":"Oceania","subregion":"Polynesia","area":47},
{"name":{"common":"Peru","official":"Republic of Peru","native":{"aym":{"official":"Piruw Suyu","common":"Piruw"},"que":{"official":"Piruw Ripuwlika","common":"Piruw"},"spa":{"official":"Rep\u00fablica del Per\u00fa","common":"Per\u00fa"}}},"cca2":"PE","independent":true,"status":"officially-assigned","currency":["PEN"],"capital":["Lima"],"region":"Americas","subregion":"South America","area":1285216},
{"name":{"common":"Philippines","official":"Republic of the Philippines","native":{"eng":{"official":"Republic of the Philippines","common":"Philippines"},"fil":{"official":"Republic of the Philippines","common":"Pilipinas"}}},"cca2":"PH","independent":true,"status":"officially-assigned","currency":["PHP"],"capital":["Manila"],"region":"Asia","subregion":"South-Eastern Asia","area":342353},
{"name":{"common":"Palau","official":"Republic of Palau","native":{"eng":{"official":"Republic of Palau","common":"Palau"},"pau":{"official":"Beluu er a Belau","common":"Belau"}}},"cca2":"PW","independent":true,"status":"officially-assigned","currency":["USD"],"capital":["Ngerulmud"],"region":"Oceania","subregion":"Micronesia","area":459},
{"name":{"common":"Papua New Guinea","official":"Independent State of Papua New Guinea","native":{"eng":{"official":"Independent State of Papua New Guinea","common":"Papua New Guinea"},"hmo":{"official":"Independen Stet bilong Papua Niugini","common":"Papua Niu Gini"},"tpi":{"official":"Independen Stet bilong Papua Niugini","common":"Papua Niugini"}}},"cca2":"PG","independent":true,"status":"officially-assigned","currency":["PGK"],"capital":["Port Moresby"],"region":"Oceania","subregion":"Melanesia","area":462840},
{"name":{"common":"Poland","official":"Republic of Poland","native":{"pol":{"official":"Rzeczpospolita Polska","common":"Polska"}}},"cca2":"PL","independent":true,"status":"officially-assigned","currency":["PLN"],"capital":["Warsaw"],"region":"Europe","subregion":"Eastern Europe","area":312679},
{"name":{"common":"Puerto Rico","official":"Commonwealth of Puerto Rico","native":{"eng":{"official":"Commonwealth of Puerto Rico","common":"Puerto Rico"},"spa":{"official":"Estado Libre Asociado de Puerto Rico","common":"Puerto Rico"}}},"cca2":"PR","independent":false,"status":"officially-assigned","currency":["USD"],"capital":["San Juan"],"region":"Americas","subregion":"Caribbean","area":8870},
{"name":{"common":"North Korea","official":"Democratic People's Republic of Korea","native":{"kor":{"official":"\uc870\uc120 \ubbfc\uc8fc\uc8fc\uc758 \uc778\ubbfc \uacf5\ud654\uad6d","common":"\ubd81\ud55c"}}},"cca2":"KP","independent":true,"status":"officially-assigned","currency":["KPW"],"capital":["Pyongyang"],"region":"Asia","subregion":"Eastern Asia","area":120538},
{"name":{"common":"Portugal","official":"Portuguese Republic","native":{"por":{"official":"Rep\u00fablica portugu\u00eas","common":"Portugal"}}},"cca2":"PT","independent":true,"status":"officially-assigned","currency":["EUR"],"capital":["Lisbon"],"region":"Europe","subregion":"Southern Europe","area":92090},
{"name":{"common":"Paraguay","official":"Republic of Paraguay","native":{"grn":{"official":"Tet\u00e3 Paragu\u00e1i","common":"Paragu\u00e1i"},"spa":{"official":"Rep\u00fablica de Paraguay","common":"Paraguay"}}},"cca2":"PY","independent":true,"status":"officially-assigned","currency":["PYG"],"capital":["Asunci\u00f3n"],"region":"Americas","subregion":"South America","area":406752},
{"name":{"common":"Palestine","official":"State of Palestine","native":{"ara":{"official":"\u062f\u0648\u0644\u0629 \u0641\u0644\u0633\u0637\u064a\u0646","common":"\u0641\u0644\u0633\u0637\u064a\u0646"}}},"cca2":"PS","independent":false,"status":"officially-assigned","currency":["ILS"],"capital":["Ramallah"],"region":"Asia","subregion":"Western Asia","area":6220},
{"name":{"common":"French Polynesia","official":"French Polynesia","native":{"fra":{"official":"Polyn\u00e9sie fran\u00e7aise","common":"Polyn\u00e9sie fran\u00e7aise"}}},"cca2":"PF","independent":false,"status":"officially-assigned","currency":["XPF"],"capital":["Papeet\u0113"],"region":"Oceania","subregion":"Polynesia","area":4167},
{"name":{"common":"Qatar","official":"State of Qatar","native":{"ara":{"official":"\u062f\u0648\u0644\u0629 \u0642\u0637\u0631","common":"\u0642\u0637\u0631"}}},"cca2":"QA","independent":true,"status":"officially-assigned","currency":["QAR"],"capital":["Doha"],"region":"Asia","subregion":"Western Asia","area":11586},
{"name":{"common":"R\u00e9union","official":"R\u00e9union Island","native":{"fra":{"official":"Ile de la R\u00e9union","common":"La R\u00e9union"}}},"cca2":"RE","independent":false,"status":"officially-assigned","currency":["EUR"],"capital":["Saint-Denis"],"region":"Africa","subregion":"Eastern Africa","area":2511},
{"name":{"common":"Romania","official":"Romania","native":{"ron":{"official":"Rom\u00e2nia","common":"Rom\u00e2nia"}}},"cca2":"RO","independent":true,"status":"officially-assigned","currency":["RON"],"capital":["Bucharest"],"region":"Europe","subregion":"Eastern Europe","area":238391},
{"name":{"common":"Russia","official":"Russian Federation","native":{"rus":{"official":"\u0420\u043e\u0441\u0441\u0438\u0439\u0441\u043a\u0430\u044f \u0424\u0435\u0434\u0435\u0440\u0430\u0446\u0438\u044f","common":"\u0420\u043e\u0441\u0441\u0438\u044f"}}},"cca2":"RU","independent":true,"status":"officially-assigned","currency":["RUB"],"capital":["Moscow"],"region":"Europe","subregion":"Eastern Europe","area":17098242},
{"name":{"common":"Rwanda","official":"Republic of Rwanda","native":{"eng":{"official":"Republic of Rwanda","common":"Rwanda"},"fra":{"official":"R\u00e9publique rwandaise","common":"Rwanda"},"kin":{"official":"Repubulika y'u Rwanda","common":"Rwanda"}}},"cca2":"RW","independent":true,"status":"officially-assigned","currency":["RWF"],"capital":["Kigali"],"region":"Africa","subregion":"Eastern Africa","area":26338},
{"name":{"common":"Saudi Arabia","official":"Kingdom of Saudi Arabia","native":{"ara":{"official":"\u0627\u0644\u0645\u0645\u0644\u0643\u0629 \u0627\u0644\u0639\u0631\u0628\u064a\u0629 \u0627\u0644\u0633\u0639\u0648\u062f\u064a\u0629","common":"\u0627\u0644\u0639\u0631\u0628\u064a\u0629 \u0627\u0644\u0633\u0639\u0648\u062f\u064a\u0629"}}},"cca2":"SA","independent":true,"status":"officially-assigned","currency":["SAR"],"capital":["Riyadh"],"region":"Asia","subregion":"Western Asia","area":2149690},
{"name":{"common":"Sudan","official":"Republic of the Sudan","native":{"ara":{"official":"\u062c\u0645\u0647\u0648\u0631\u064a\u0629 \u0627\u0644\u0633\u0648\u062f\u0627\u0646","common":"\u0627\u0644\u0633\u0648\u062f\u0627\u0646"},"eng":{"official":"Republic of the Sudan","common":"Sudan"}}},"cca2":"SD","independent":true,"status":"officially-assigned","currency":["SDG"],"capital":["Khartoum"],"region":"Africa","subregion":"Northern Africa","area":1886068},
{"name":{"common":"Senegal","official":"Republic of Senegal","native":{"fra":{"official":"R\u00e9publique du S\u00e9n\u00e9gal","common":"S\u00e9n\u00e9gal"}}},"cca2":"SN","independent":true,"status":"officially-assigned","currency":["XOF"],"capital":["Dakar"],"region":"Africa","subregion":"Western Africa","area":196722},
{"name":{"common":"Singapore","official":"Republic of Singapore","native":{"zho":{"official":"\u65b0\u52a0\u5761\u5171\u548c\u56fd","common":"\u65b0\u52a0\u5761"},"eng":{"official":"Republic of Singapore","common":"Singapore"},"msa":{"official":"Republik Singapura","common":"Singapura"},"tam":{"official":"\u0b9a\u0bbf\u0b99\u0bcd\u0b95\u0baa\u0bcd\u0baa\u0bc2\u0bb0\u0bcd \u0b95\u0bc1\u0b9f\u0bbf\u0baf\u0bb0\u0b9a\u0bc1","common":"\u0b9a\u0bbf\u0b99\u0bcd\u0b95\u0baa\u0bcd\u0baa\u0bc2\u0bb0\u0bcd"}}},"cca2":"SG","independent":true,"status":"officially-assigned","currency":["SGD"],"capital":["Singapore"],"region":"Asia","subregion":"South-Eastern Asia","area":710},
{"name":{"common":"South Georgia","official":"South Georgia and the South Sandwich Islands","native":{"eng":{"official":"South Georgia and the South Sandwich Islands","common":"South Georgia"}}},"cca2":"GS","independent":false,"status":"officially-assigned","currency":["GBP"],"capital":["King Edward Point"],"region":"Antarctic","subregion":"","area":3903},
{"name":{"common":"Svalbard and Jan Mayen","official":"Svalbard og Jan Mayen","native":{"nor":{"official":"Svalbard og Jan Mayen","common":"Svalbard og Jan Mayen"}}},"cca2":"SJ","independent":false,"status":"officially-assigned","currency":["NOK"],"capital":["Longyearbyen"],"region":"Europe","subregion":"Northern Europe","area":-1},
{"name":{"common":"Solomon Islands","official":"Solomon Islands","native":{"eng":{"official":"Solomon Islands","common":"Solomon Islands"}}},"cca2":"SB","independent":true,"status":"officially-assigned","currency":["SBD"],"capital":["Honiara"],"region":"Oceania","subregion":"Melanesia","area":28896},
{"name":{"common":"Sierra Leone","official":"Republic of Sierra Leone","native":{"eng":{"official":"Republic of Sierra Leone","common":"Sierra Leone"}}},"cca2":"SL","independent":true,"status":"officially-assigned","currency":["SLL"],"capital":["Freetown"],"region":"Africa","subregion":"Western Africa","area":71740},
{"name":{"common":"El Salvador","official":"Republic of El Salvador","native":{"spa":{"official":"Rep\u00fablica de El Salvador","common":"El Salvador"}}},"cca2":"SV","independent":true,"status":"officially-assigned","currency":["SVC","USD"],"capital":["San Salvador"],"region":"Americas","subregion":"Central America","area":21041},
{"name":{"common":"San Marino","official":"Most Serene Republic of San Marino","native":{"ita":{"official":"Serenissima Repubblica di San Marino","common":"San Marino"}}},"cca2":"SM","independent":true,"status":"officially-assigned","currency":["EUR"],"capital":["City of San Marino"],"region":"Europe","subregion":"Southern Europe","area":61},
{"name":{"common":"Somalia","official":"Federal Republic of Somalia","native":{"ara":{"official":"\u062c\u0645\u0647\u0648\u0631\u064a\u0629 \u0627\u0644\u0635\u0648\u0645\u0627\u0644\u200e\u200e","common":"\u0627\u0644\u0635\u0648\u0645\u0627\u0644\u200e\u200e"},"som":{"official":"Jamhuuriyadda Federaalka Soomaaliya","common":"Soomaaliya"}}},"cca2":"SO","independent":true,"status":"officially-assigned","currency":["SOS"],"capital":["Mogadishu"],"region":"Africa","subregion":"Eastern Africa","area":637657},
{"name":{"common":"Saint Pierre and Miquelon","official":"Saint Pierre and Miquelon","native":{"fra":{"official":"Collectivit\u00e9 territoriale de Saint-Pierre-et-Miquelon","common":"Saint-Pierre-et-Miquelon"}}},"cca2":"PM","independent":false,"status":"officially-assigned","currency":["EUR"],"capital":["Saint-Pierre"],"region":"Americas","subregion":"Northern America","area":242},
{"name":{"common":"Serbia","official":"Republic of Serbia","native":{"srp":{"official":"\u0420\u0435\u043f\u0443\u0431\u043b\u0438\u043a\u0430 \u0421\u0440\u0431\u0438\u0458\u0430","common":"\u0421\u0440\u0431\u0438\u0458\u0430"}}},"cca2":"RS","independent":true,"status":"officially-assigned","currency":["RSD"],"capital":["Belgrade"],"region":"Europe","subregion":"Southern Europe","area":88361},
{"name":{"common":"South Sudan","official":"Republic of South Sudan","native":{"eng":{"official":"Republic of South Sudan","common":"South Sudan"}}},"cca2":"SS","independent":true,"status":"officially-assigned","currency":["SSP"],"capital":["Juba"],"region":"Africa","subregion":"Middle Africa","area":619745},
{"name":{"common":"S\u00e3o Tom\u00e9 and Pr\u00edncipe","official":"Democratic Republic of S\u00e3o Tom\u00e9 and Pr\u00edncipe","native":{"por":{"official":"Rep\u00fablica Democr\u00e1tica do S\u00e3o Tom\u00e9 e Pr\u00edncipe","common":"S\u00e3o Tom\u00e9 e Pr\u00edncipe"}}},"cca2":"ST","independent":true,"status":"officially-assigned","currency":["STD"],"capital":["S\u00e3o Tom\u00e9"],"region":"Africa","subregion":"Middle Africa","area":964},
{"name":{"common":"Suriname","official":"Republic of Suriname","native":{"nld":{"official":"Republiek Suriname","common":"Suriname"}}},"cca2":"SR","independent":true,"status":"officially-assigned","currency":["SRD"],"capital":["Paramaribo"],"region":"Americas","subregion":"South America","area":163820},
{"name":{"common":"Slovakia","official":"Slovak Republic","native":{"slk":{"official":"Slovensk\u00e1 republika","common":"Slovensko"}}},"cca2":"SK","independent":true,"status":"officially-assigned","currency":["EUR"],"capital":["Bratislava"],"region":"Europe","subregion":"Central Europe","area":49037},
{"name":{"common":"Slovenia","official":"Republic of Slovenia","native":{"slv":{"official":"Republika Slovenija","common":"Slovenija"}}},"cca2":"SI","independent":true,"status":"officially-assigned","currency":["EUR"],"capital":["Ljubljana"],"region":"Europe","subregion":"Southern Europe","area":20273},
{"name":{"common":"Sweden","official":"Kingdom of Sweden","native":{"swe":{"official":"Konungariket Sverige","common":"Sverige"}}},"cca2":"SE","independent":true,"status":"officially-assigned","currency":["SEK"],"capital":["Stockholm"],"region":"Europe","subregion":"Northern Europe","area":450295},
{"name":{"common":"Swaziland","official":"Kingdom of Swaziland","native":{"eng":{"official":"Kingdom of Swaziland","common":"Swaziland"},"ssw":{"official":"Kingdom of Swaziland","common":"Swaziland"}}},"cca2":"SZ","independent":true,"status":"officially-assigned","currency":["SZL"],"capital":["Lobamba"],"region":"Africa","subregion":"Southern Africa","area":17364},
{"name":{"common":"Sint Maarten","official":"Sint Maarten","native":{"eng":{"official":"Sint Maarten","common":"Sint Maarten"},"fra":{"official":"Saint-Martin","common":"Saint-Martin"},"nld":{"official":"Sint Maarten","common":"Sint Maarten"}}},"cca2":"SX","independent":false,"status":"officially-assigned","currency":["ANG"],"capital":["Philipsburg"],"region":"Americas","subregion":"Caribbean","area":34},
{"name":{"common":"Seychelles","official":"Republic of Seychelles","native":{"crs":{"official":"Repiblik Sesel","common":"Sesel"},"eng":{"official":"Republic of Seychelles","common":"Seychelles"},"fra":{"official":"R\u00e9publique des Seychelles","common":"Seychelles"}}},"cca2":"SC","independent":true,"status":"officially-assigned","currency":["SCR"],"capital":["Victoria"],"region":"Africa","subregion":"Eastern Africa","area":452},
{"name":{"common":"Syria","official":"Syrian Arab Republic","native":{"ara":{"official":"\u0627\u0644\u062c\u0645\u0647\u0648\u0631\u064a\u0629 \u0627\u0644\u0639\u0631\u0628\u064a\u0629 \u0627\u0644\u0633\u0648\u0631\u064a\u0629","common":"\u0633\u0648\u0631\u064a\u0627"}}},"cca2":"SY","independent":true,"status":"officially-assigned","currency":["SYP"],"capital":["Damascus"],"region":"Asia","subregion":"Western Asia","area":185180},
{"name":{"common":"Turks and Caicos Islands","official":"Turks and Caicos Islands","native":{"eng":{"official":"Turks and Caicos Islands","common":"Turks and Caicos Islands"}}},"cca2":"TC","independent":false,"status":"officially-assigned","currency":["USD"],"capital":["Cockburn Town"],"region":"Americas","subregion":"Caribbean","area":948},
{"name":{"common":"Chad","official":"Republic of Chad","native":{"ara":{"official":"\u062c\u0645\u0647\u0648\u0631\u064a\u0629 \u062a\u0634\u0627\u062f","common":"\u062a\u0634\u0627\u062f\u200e"},"fra":{"official":"R\u00e9publique du Tchad","common":"Tchad"}}},"cca2":"TD","independent":true,"status":"officially-assigned","currency":["XAF"],"capital":["N'Djamena"],"region":"Africa","subregion":"Middle Africa","area":1284000},
{"name":{"common":"Togo","official":"Togolese Republic","native":{"fra":{"official":"R\u00e9publique togolaise","common":"Togo"}}},"cca2":"TG","independent":true,"status":"officially-assigned","currency":["XOF"],"capital":["Lom\u00e9"],"region":"Africa","subregion":"Western Africa","area":56785},
{"name":{"common":"Thailand","official":"Kingdom of Thailand","native":{"tha":{"official":"\u0e23\u0e32\u0e0a\u0e2d\u0e32\u0e13\u0e32\u0e08\u0e31\u0e01\u0e23\u0e44\u0e17\u0e22","common":"\u0e1b\u0e23\u0e30\u0e40\u0e17\u0e28\u0e44\u0e17\u0e22"}}},"cca2":"TH","independent":true,"status":"officially-assigned","currency":["THB"],"capital":["Bangkok"],"region":"Asia","subregion":"South-Eastern Asia","area":513120},
{"name":{"common":"Tajikistan","official":"Republic of Tajikistan","native":{"rus":{"official":"\u0420\u0435\u0441\u043f\u0443\u0431\u043b\u0438\u043a\u0430 \u0422\u0430\u0434\u0436\u0438\u043a\u0438\u0441\u0442\u0430\u043d","common":"\u0422\u0430\u0434\u0436\u0438\u043a\u0438\u0441\u0442\u0430\u043d"},"tgk":{"official":"\u04b6\u0443\u043c\u04b3\u0443\u0440\u0438\u0438 \u0422\u043e\u04b7\u0438\u043a\u0438\u0441\u0442\u043e\u043d","common":"\u0422\u043e\u04b7\u0438\u043a\u0438\u0441\u0442\u043e\u043d"}}},"cca2":"TJ","independent":true,"status":"officially-assigned","currency":["TJS"],"capital":["Dushanbe"],"region":"Asia","subregion":"Central Asia","area":143100},
{"name":{"common":"Tokelau","official":"Tokelau","native":{"eng":{"official":"Tokelau","common":"Tokelau"},"smo":{"official":"Tokelau","common":"Tokelau"},"tkl":{"official":"Tokelau","common":"Tokelau"}}},"cca2":"TK","independent":false,"status":"officially-assigned","currency":["NZD"],"capital":["Fakaofo"],"region":"Oceania","subregion":"Polynesia","area":12},
{"name":{"common":"Turkmenistan","official":"Turkmenistan","native":{"rus":{"official":"\u0422\u0443\u0440\u043a\u043c\u0435\u043d\u0438\u0441\u0442\u0430\u043d","common":"\u0422\u0443\u0440\u043a\u043c\u0435\u043d\u0438\u044f"},"tuk":{"official":"T\u00fcrkmenistan","common":"T\u00fcrkmenistan"}}},"cca2":"TM","independent":true,"status":"officially-assigned","currency":["TMT"],"capital":["Ashgabat"],"region":"Asia","subregion":"Central Asia","area":488100},
{"name":{"common":"Timor-Leste","official":"Democratic Republic of Timor-Leste","native":{"por":{"official":"Rep\u00fablica Democr\u00e1tica de Timor-Leste","common":"Timor-Leste"},"tet":{"official":"Rep\u00fablika Demokr\u00e1tika Tim\u00f3r-Leste","common":"Tim\u00f3r-Leste"}}},"cca2":"TL","independent":true,"status":"officially-assigned","currency":["USD"],"capital":["Dili"],"region":"Asia","subregion":"South-Eastern Asia","area":14874},
{"name":{"common":"Tonga","official":"Kingdom of Tonga","native":{"eng":{"official":"Kingdom of Tonga","common":"Tonga"},"ton":{"official":"Kingdom of Tonga","common":"Tonga"}}},"cca2":"TO","independent":true,"status":"officially-assigned","currency":["TOP"],"capital":["Nuku'alofa"],"region":"Oceania","subregion":"Polynesia","area":747},
{"name":{"common":"Trinidad and Tobago","official":"Republic of Trinidad and Tobago","native":{"eng":{"official":"Republic of Trinidad and Tobago","common":"Trinidad and Tobago"}}},"cca2":"TT","independent":true,"status":"officially-assigned","currency":["TTD"],"capital":["Port of Spain"],"region":"Americas","subregion":"Caribbean","area":5130},
{"name":{"common":"Tunisia","official":"Tunisian Republic","native":{"ara":{"official":"\u0627\u0644\u062c\u0645\u0647\u0648\u0631\u064a\u0629 \u0627\u0644\u062a\u0648\u0646\u0633\u064a\u0629","common":"\u062a\u0648\u0646\u0633"}}},"cca2":"TN","independent":true,"status":"officially-assigned","currency":["TND"],"capital":["Tunis"],"region":"Africa","subregion":"Northern Africa","area":163610},
{"name":{"common":"Turkey","official":"Republic of Turkey","native":{"tur":{"official":"T\u00fcrkiye Cumhuriyeti","common":"T\u00fcrkiye"}}},"cca2":"TR","independent":true,"status":"officially-assigned","currency":["TRY"],"capital":["Ankara"],"region":"Asia","subregion":"Western Asia","area":783562},
{"name":{"common":"Tuvalu","official":"Tuvalu","native":{"eng":{"official":"Tuvalu","common":"Tuvalu"},"tvl":{"official":"Tuvalu","common":"Tuvalu"}}},"cca2":"TV","independent":true,"status":"officially-assigned","currency":["AUD"],"capital":["Funafuti"],"region":"Oceania","subregion":"Polynesia","area":26},
{"name":{"common":"Taiwan","official":"Republic of China (Taiwan)","native":{"zho":{"official":"\u4e2d\u83ef\u6c11\u570b","common":"\u53f0\u7063"}}},"cca2":"TW","independent":false,"status":"officially-assigned","currency":["TWD"],"capital":["Taipei"],"region":"Asia","subregion":"Eastern Asia","area":36193},
{"name":{"common":"Tanzania","official":"United Republic of Tanzania","native":{"eng":{"official":"United Republic of Tanzania","common":"Tanzania"},"swa":{"official":"Jamhuri ya Muungano wa Tanzania","common":"Tanzania"}}},"cca2":"TZ","independent":true,"status":"officially-assigned","currency":["TZS"],"capital":["Dodoma"],"region":"Africa","subregion":"Eastern Africa","area":945087},
{"name":{"common":"Uganda","official":"Republic of Uganda","native":{"eng":{"official":"Republic of Uganda","common":"Uganda"},"swa":{"official":"Republic of Uganda","common":"Uganda"}}},"cca2":"UG","independent":true,"status":"officially-assigned","currency":["UGX"],"capital":["Kampala"],"region":"Africa","subregion":"Eastern Africa","area":241550},
{"name":{"common":"Ukraine","official":"Ukraine","native":{"ukr":{"official":"\u0423\u043a\u0440\u0430\u0457\u043d\u0430","common":"\u0423\u043a\u0440\u0430\u0457\u043d\u0430"}}},"cca2":"UA","independent":true,"status":"officially-assigned","currency":["UAH"],"capital":["Kyiv"],"region":"Europe","subregion":"Eastern Europe","area":603500},
{"name":{"common":"United States Minor Outlying Islands","official":"United States Minor Outlying Islands","native":{"eng":{"official":"United States Minor Outlying Islands","common":"United States Minor Outlying Islands"}}},"cca2":"UM","independent":false,"status":"officially-assigned","currency":["USD"],"capital":[""],"region":"Americas","subregion":"Northern America","area":34.2},
{"name":{"common":"Uruguay","official":"Oriental Republic of Uruguay","native":{"spa":{"official":"Rep\u00fablica Oriental del Uruguay","common":"Uruguay"}}},"cca2":"UY","independent":true,"status":"officially-assigned","currency":["UYI","UYU"],"capital":["Montevideo"],"region":"Americas","subregion":"South America","area":181034},
{"name":{"common":"United States","official":"United States of America","native":{"eng":{"official":"United States of America","common":"United States"}}},"cca2":"US","independent":true,"status":"officially-assigned","currency":["USD","USN","USS"],"capital":["Washington D.C."],"region":"Americas","subregion":"Northern America","area":9372610},
{"name":{"common":"Uzbekistan","official":"Republic of Uzbekistan","native":{"rus":{"official":"\u0420\u0435\u0441\u043f\u0443\u0431\u043b\u0438\u043a\u0430 \u0423\u0437\u0431\u0435\u043a\u0438\u0441\u0442\u0430\u043d","common":"\u0423\u0437\u0431\u0435\u043a\u0438\u0441\u0442\u0430\u043d"},"uzb":{"official":"O'zbekiston Respublikasi","common":"O\u2018zbekiston"}}},"cca2":"UZ","independent":true,"status":"officially-assigned","currency":["UZS"],"capital":["Tashkent"],"region":"Asia","subregion":"Central Asia","area":447400},
{"name":{"common":"Vatican City","official":"Vatican City State","native":{"ita":{"official":"Stato della Citt\u00e0 del Vaticano","common":"Vaticano"},"lat":{"official":"Status Civitatis Vatican\u00e6","common":"Vatican\u00e6"}}},"cca2":"VA","independent":true,"status":"officially-assigned","currency":["EUR"],"capital":["Vatican City"],"region":"Europe","subregion":"Southern Europe","area":0.44},
{"name":{"common":"Saint Vincent and the Grenadines","official":"Saint Vincent and the Grenadines","native":{"eng":{"official":"Saint Vincent and the Grenadines","common":"Saint Vincent and the Grenadines"}}},"cca2":"VC","independent":true,"status":"officially-assigned","currency":["XCD"],"capital":["Kingstown"],"region":"Americas","subregion":"Caribbean","area":389},
{"name":{"common":"Venezuela","official":"Bolivarian Republic of Venezuela","native":{"spa":{"official":"Rep\u00fablica Bolivariana de Venezuela","common":"Venezuela"}}},"cca2":"VE","independent":true,"status":"officially-assigned","currency":["VEF"],"capital":["Caracas"],"region":"Americas","subregion":"South America","area":916445},
{"name":{"common":"British Virgin Islands","official":"Virgin Islands","native":{"eng":{"official":"Virgin Islands","common":"British Virgin Islands"}}},"cca2":"VG","independent":false,"status":"officially-assigned","currency":["USD"],"capital":["Road Town"],"region":"Americas","subregion":"Caribbean","area":151},
{"name":{"common":"United States Virgin Islands","official":"Virgin Islands of the United States","native":{"eng":{"official":"Virgin Islands of the United States","common":"United States Virgin Islands"}}},"cca2":"VI","independent":false,"status":"officially-assigned","currency":["USD"],"capital":["Charlotte Amalie"],"region":"Americas","subregion":"Caribbean","area":347},
{"name":{"common":"Vietnam","official":"Socialist Republic of Vietnam","native":{"vie":{"official":"C\u1ed9ng h\u00f2a x\u00e3 h\u1ed9i ch\u1ee7 ngh\u0129a Vi\u1ec7t Nam","common":"Vi\u1ec7t Nam"}}},"cca2":"VN","independent":true,"status":"officially-assigned","currency":["VND"],"capital":["Hanoi"],"region":"Asia","subregion":"South-Eastern Asia","area":331212},
{"name":{"common":"Vanuatu","official":"Republic of Vanuatu","native":{"bis":{"official":"Ripablik blong Vanuatu","common":"Vanuatu"},"eng":{"official":"Republic of Vanuatu","common":"Vanuatu"},"fra":{"official":"R\u00e9publique de Vanuatu","common":"Vanuatu"}}},"cca2":"VU","independent":true,"status":"officially-assigned","currency":["VUV"],"capital":["Port Vila"],"region":"Oceania","subregion":"Melanesia","area":12189},
{"name":{"common":"Wallis and Futuna","official":"Territory of the Wallis and Futuna Islands","native":{"fra":{"official":"Territoire des \u00eeles Wallis et Futuna","common":"Wallis et Futuna"}}},"cca2":"WF","independent":false,"status":"officially-assigned","currency":["XPF"],"capital":["Mata-Utu"],"region":"Oceania","subregion":"Polynesia","area":142},
{"name":{"common":"Samoa","official":"Independent State of Samoa","native":{"eng":{"official":"Independent State of Samoa","common":"Samoa"},"smo":{"official":"Malo Sa\u02bboloto Tuto\u02bbatasi o S\u0101moa","common":"S\u0101moa"}}},"cca2":"WS","independent":true,"status":"officially-assigned","currency":["WST"],"capital":["Apia"],"region":"Oceania","subregion":"Polynesia","area":2842},
{"name":{"common":"Yemen","official":"Republic of Yemen","native":{"ara":{"official":"\u0627\u0644\u062c\u0645\u0647\u0648\u0631\u064a\u0629 \u0627\u0644\u064a\u0645\u0646\u064a\u0629","common":"\u0627\u0644\u064a\u064e\u0645\u064e\u0646"}}},"cca2":"YE","independent":true,"status":"officially-assigned","currency":["YER"],"capital":["Sana'a"],"region":"Asia","subregion":"Western Asia","area":527968},
{"name":{"common":"South Africa","official":"Republic of South Africa","native":{"afr":{"official":"Republiek van Suid-Afrika","common":"South Africa"},"eng":{"official":"Republic of South Africa","common":"South Africa"},"nbl":{"official":"IRiphabliki yeSewula Afrika","common":"Sewula Afrika"},"nso":{"official":"Rephaboliki ya Afrika-Borwa ","common":"Afrika-Borwa"},"sot":{"official":"Rephaboliki ya Afrika Borwa","common":"Afrika Borwa"},"ssw":{"official":"IRiphabhulikhi yeNingizimu Afrika","common":"Ningizimu Afrika"},"tsn":{"official":"Rephaboliki ya Aforika Borwa","common":"Aforika Borwa"},"tso":{"official":"Riphabliki ra Afrika Dzonga","common":"Afrika Dzonga"},"ven":{"official":"Riphabu\u1e3diki ya Afurika Tshipembe","common":"Afurika Tshipembe"},"xho":{"official":"IRiphabliki yaseMzantsi Afrika","common":"Mzantsi Afrika"},"zul":{"official":"IRiphabliki yaseNingizimu Afrika","common":"Ningizimu Afrika"}}},"cca2":"ZA","independent":true,"status":"officially-assigned","currency":["ZAR"],"capital":["Pretoria","Bloemfontein","Cape Town"],"region":"Africa","subregion":"Southern Africa","area":1221037},
{"name":{"common":"Zambia","official":"Republic of Zambia","native":{"eng":{"official":"Republic of Zambia","common":"Zambia"}}},"cca2":"ZM","independent":true,"status":"officially-assigned","currency":["ZMW"],"capital":["Lusaka"],"region":"Africa","subregion":"Eastern Africa","area":752612},
{"name":{"common":"Zimbabwe","official":"Republic of Zimbabwe","native":{"bwg":{"official":"Republic of Zimbabwe","common":"Zimbabwe"},"eng":{"official":"Republic of Zimbabwe","common":"Zimbabwe"},"kck":{"official":"Republic of Zimbabwe","common":"Zimbabwe"},"khi":{"official":"Republic of Zimbabwe","common":"Zimbabwe"},"ndc":{"official":"Republic of Zimbabwe","common":"Zimbabwe"},"nde":{"official":"Republic of Zimbabwe","common":"Zimbabwe"},"nya":{"official":"Republic of Zimbabwe","common":"Zimbabwe"},"sna":{"official":"Republic of Zimbabwe","common":"Zimbabwe"},"sot":{"official":"Republic of Zimbabwe","common":"Zimbabwe"},"toi":{"official":"Republic of Zimbabwe","common":"Zimbabwe"},"tsn":{"official":"Republic of Zimbabwe","common":"Zimbabwe"},"tso":{"official":"Republic of Zimbabwe","common":"Zimbabwe"},"ven":{"official":"Republic of Zimbabwe","common":"Zimbabwe"},"xho":{"official":"Republic of Zimbabwe","common":"Zimbabwe"},"zib":{"official":"Republic of Zimbabwe","common":"Zimbabwe"}}},"cca2":"ZW","independent":true,"status":"officially-assigned","currency":["ZWL"],"capital":["Harare"],"region":"Africa","subregion":"Eastern Africa","area":390757}]
